Workbook

Sheet Export original
B1: LUIS T. - S.R.L.
A4: 39100 Bolzano | B4: Tax code | C4: 02274840210
B5: CCIAA number | C5: BZ0167343
A6: Private company
A7: The Global Ultimate Owner of this controlled subsidiary is MR MARKUS BAUMGARTNER
A10: Contact details
A13: Registered office address
A14: WERNER-VON-SIEMENS-STRASSE, 18 | B14: Phone number | C14: 0471095564
A15: 39100 Bolzano | B15: Website address | C15: =HYPERLINK("http://www.luistrenker.com/","www.luistrenker.com") -> www.luistrenker.com
A16: BOLZANO/BOZEN(TRENTINO-ALTO ADIGE/SÜDTIROL)
A18: Trading address
A19: VIA VON SIEMENS 18 | B19: Phone number | C19: 0471095564
A20: 39100 Bolzano
A21: BOLZANO/BOZEN(TRENTINO-ALTO ADIGE)
A24: Legal & account information
A27: Previous name
A28: 08/2012 | B28: LUIS T. - S.R.L. % LUIS T. G.M.B.H.
A29: The date of name change has no legal validity but is the date BvD detected the name change
A31: Legal status | B31: Active | C31: Last accounting closing date | D31: 31/03/2025
A32: Legal form | B32: Limited liability company - SRL
C33: No of available years | D33: 10
A34: Date of incorporation | B34: 37077 | C34: Available accounts | D34: Unconsolidated
C35: Last accounting model | D35: Detailed
A38: Size and group information
A41: Turnover (2025) | B41: 14.885.328 EUR | C41: BvD independence indicator | D41: D
A42: Profit (loss) (2025) | B42: 160.035 EUR
C43: No of companies in corporate group | D43: 7
A44: Total assets (2025) | B44: 12.930.506 EUR
A45: Employees (2025) | B45: 52
C46: No of recorded shareholders | D46: 4
A47: Social capital (2025) | B47: 100 th EUR
C49: No of recorded subsidiaries | D49: 2
A51: Main exchange | B51: Unlisted
A54: Industry classification
A57: Italian trade description | B57: CONFEZIONE DI ARTICOLI DI ABBIGLIAMENTO (ESCLUSO ABBIGLIAMENTO IN LLICCIA)
A59: Ateco 2007 code | B59: 141000 Manufacture of wearing apparel, except fur apparel
A61: SAE code | B61: 430 Imprese produttive
A63: RAE code | B63: 453 Articoli di abbigliamento ed accessori
A66: Peer group
A69: Name | B69: 141 VL (Very large companies)
A70: Description | B70: Confezione di articoli di abbigliamento (escluso abbligliamento in pelliccia)
A71: Size | B71: 1.742 companies
A74: Key financials & employees
B76: Unconsolidated | C76: 31/03/2025 EUR | D76: 31/03/2024 EUR | E76: 31/03/2023 EUR | F76: 31/03/2022 EUR | G76: 31/03/2021 EUR | H76: 31/03/2020 EUR | I76: 31/03/2019 EUR | J76: 31/03/2018 EUR | K76: 31/03/2017 EUR | L76: 31/03/2016 EUR
C77: 12 months Detailed ICS | D77: 12 months Detailed ICS | E77: 12 months Detailed ICS | F77: 12 months Detailed ICS | G77: 12 months Detailed ICS | H77: 12 months Detailed ICS | I77: 12 months Detailed ICS | J77: 12 months Abbreviated (D) ICS | K77: 12 months Abbreviated (D) ICS | L77: 12 months Abbreviated (D) ICS
B79: Revenues from sales and services | C79: 14885328 | D79: 14294364 | E79: 13782014 | F79: 11619465 | G79: 8552816 | H79: 9712939 | I79: 10220941 | J79: 8912701 | K79: 7807091 | L79: 6287625
B80: EBITDA | C80: 1062376 | D80: 1513067 | E80: 1608701 | F80: 1473280 | G80: 889518 | H80: 701754 | I80: 595594 | J80: 670640 | K80: 532113 | L80: 445108
B81: Profit (loss) | C81: 160035 | D81: 672289 | E81: 776780 | F81: 513808 | G81: 304750 | H81: 19704 | I81: 209448 | J81: 256820 | K81: 164166 | L81: 124157
B82: Total assets | C82: 12930506 | D82: 11990730 | E82: 10877098 | F82: 8985482 | G82: 7250567 | H82: 6831833 | I82: 7194117 | J82: 5269792 | K82: 4342288 | L82: 4392744
B83: Total shareholder's funds | C83: 3089801 | D83: 2929765 | E83: 2257478 | F83: 1480696 | G83: 966890 | H83: 662137 | I83: 642433 | J83: 432985 | K83: 176166 | L83: 320323
B84: Net financial position | C84: 5455097 | D84: 5886637 | E84: 4714792 | F84: 4399459 | G84: 2565050 | H84: 2849112 | I84: 3938981 | J84: 1176954 | K84: 749968 | L84: 862739
B86: EBITDA/vendite (%) | C86: 6.9 | D86: 10.12 | E86: 11.12 | F86: 11.64 | G86: 9.62 | H86: 6.64 | I86: 5.59 | J86: 7.24 | K86: 6.57 | L86: 6.83
B87: Return on sales (ROS) (%) | C87: 3.56 | D87: 7.4 | E87: 8.68 | F87: 7.02 | G87: 5.92 | H87: 2.92 | I87: 4.56 | J87: 5.89 | K87: 5.43 | L87: 5.49
B88: Return on asset (ROA) (%) | C88: 4.24 | D88: 9.23 | E88: 11.54 | F88: 9.89 | G88: 7.54 | H88: 4.52 | I88: 6.75 | J88: 10.35 | K88: 10.12 | L88: 8.15
B89: Return on equity (ROE) (%) | C89: 5.18 | D89: 22.95 | E89: 34.41 | F89: 34.7 | G89: 31.52 | H89: 2.98 | I89: 32.6 | J89: 59.31 | K89: 93.19 | L89: 38.76
B90: Debt/equity ratio | C90: 2.16 | D90: 2.15 | E90: 2.38 | F90: 3.03 | G90: 3.1 | H90: 4.41 | I90: 6.2 | J90: 2.88 | K90: 4.44 | L90: 2.76
B91: Banks/turnover (%) | C91: 36.49 | D91: 35.17 | E91: 28.68 | F91: 25.19 | G91: 32.45 | H91: 27.67 | I91: 25.15 | J91: 13.44 | K91: 9.66 | L91: 13.55
... B95: Number of employees | C95: 52 | D95: 48 | E95: 42 | F95: 40 | G95: 38 | H95: 36 | I95: 25 | J95: 19 | K95: 15 | L95: 15
A98: Balance sheet
B100: Unconsolidated | C100: 31/03/2025 EUR | D100: 31/03/2024 EUR | E100: 31/03/2023 EUR | F100: 31/03/2022 EUR | G100: 31/03/2021 EUR | H100: 31/03/2020 EUR | I100: 31/03/2019 EUR | J100: 31/03/2018 EUR | K100: 31/03/2017 EUR | L100: 31/03/2016 EUR
C101: 12 months Detailed ICS | D101: 12 months Detailed ICS | E101: 12 months Detailed ICS | F101: 12 months Detailed ICS | G101: 12 months Detailed ICS | H101: 12 months Detailed ICS | I101: 12 months Detailed ICS | J101: 12 months Abbreviated (D) ICS | K101: 12 months Abbreviated (D) ICS | L101: 12 months Abbreviated (D) ICS
B102: Assets
B103: A. TOTAL receivables due from shareholders | C103: 0 | D103: 0 | E103: 0 | F103: 0 | G103: 0 | H103: 0 | I103: 0 | J103: 0 | K103: 0 | L103: 0
B104: Called share capital | C104: 0 | D104: 0 | E104: 0 | F104: 0 | G104: 0 | H104: 0 | I104: 0 | J104: 0 | K104: 0 | L104: 0
B106: B. TOTAL FIXED ASSETS | C106: 2157604 | D106: 1597153 | E106: 1533059 | F106: 836581 | G106: 563008 | H106: 577699 | I106: 692542 | J106: 644223 | K106: 276336 | L106: 303839
B107: B.I. TOTAL INTANGIBLE FIXED ASSETS | C107: 1446204 | D107: 947984 | E107: 1141024 | F107: 494303 | G107: 348629 | H107: 412309 | I107: 438786 | J107: 470038 | K107: 82026 | L107: 117794
B108: B.I.1. Start-up and expansion costs | C108: 0 | D108: 0 | E108: 0 | F108: 0 | G108: 0 | H108: 0 | I108: 0 | J108: n.a. | K108: n.a. | L108: n.a.
B109: B.I.2. Research and dev. exp. | C109: 0 | D109: 0 | E109: 0 | F109: 0 | G109: 0 | H109: 0 | I109: 0 | J109: n.a. | K109: n.a. | L109: n.a.
B110: B.I.3. Ind. patents and intellect. property rights | C110: 457183 | D110: 378595 | E110: 502430 | F110: 0 | G110: 7776 | H110: 2500 | I110: 8000 | J110: n.a. | K110: n.a. | L110: n.a.
B111: B.I.4. Concessions, licenses, trademarks and similar rights | C111: 303484 | D111: 31737 | E111: 30220 | F111: 23054 | G111: 24644 | H111: 22091 | I111: 18364 | J111: n.a. | K111: n.a. | L111: n.a.
B112: B.I.5. Goodwill/Consolidation Difference | C112: 0 | D112: 320 | E112: 755 | F112: 1190 | G112: 1625 | H112: 2059 | I112: 2494 | J112: n.a. | K112: n.a. | L112: n.a.
B113: including: Goodwill | C113: 0 | D113: 320 | E113: 755 | F113: 1190 | G113: 1625 | H113: 2059 | I113: 2494 | J113: n.a. | K113: n.a. | L113: n.a.
B114: B.I.6. Additions in progress and advances | C114: 0 | D114: 0 | E114: 0 | F114: 0 | G114: 0 | H114: 0 | I114: 0 | J114: n.a. | K114: n.a. | L114: n.a.
B115: B.I.7. Others | C115: 685537 | D115: 537332 | E115: 607619 | F115: 470059 | G115: 314584 | H115: 385659 | I115: 409928 | J115: n.a. | K115: n.a. | L115: n.a.
B116: (Amortization provision) | C116: n.a. | D116: n.a. | E116: n.a. | F116: n.a. | G116: n.a. | H116: n.a. | I116: n.a. | J116: 637202 | K116: 560857 | L116: 516308
B118: B.II. TOTAL TANGIBLE FIXED ASSETS | C118: 661130 | D118: 598899 | E118: 341765 | F118: 292008 | G118: 164109 | H118: 115120 | I118: 114391 | J118: 123915 | K118: 144040 | L118: 160775
B119: including: leased tangible assets | C119: n.a. | D119: n.a. | E119: n.a. | F119: n.a. | G119: n.a. | H119: n.a. | I119: n.a. | J119: n.a. | K119: n.a. | L119: n.a.
B120: B.II.1. Land and buildings | C120: 0 | D120: 0 | E120: 0 | F120: 0 | G120: 0 | H120: 0 | I120: 0 | J120: n.a. | K120: n.a. | L120: n.a.
B121: B.II.2. Plant and machinery | C121: 0 | D121: 0 | E121: 0 | F121: 0 | G121: 0 | H121: 0 | I121: 0 | J121: n.a. | K121: n.a. | L121: n.a.
B122: B.II.3. Indust. and commercial equipment | C122: 566644 | D122: 473049 | E122: 315454 | F122: 271989 | G122: 103437 | H122: 97013 | I122: 89836 | J122: n.a. | K122: n.a. | L122: n.a.
B123: B.II.4. Other assets | C123: 94486 | D123: 125850 | E123: 26311 | F123: 20019 | G123: 60672 | H123: 18107 | I123: 24555 | J123: n.a. | K123: n.a. | L123: n.a.
B124: B.II.5. Additions in progress and advances | C124: 0 | D124: 0 | E124: 0 | F124: 0 | G124: 0 | H124: 0 | I124: 0 | J124: n.a. | K124: n.a. | L124: n.a.
B125: (Depreciation provision) | C125: n.a. | D125: n.a. | E125: n.a. | F125: n.a. | G125: n.a. | H125: n.a. | I125: n.a. | J125: 341146 | K125: 293996 | L125: 245698
B127: B.III. TOTAL FINANCIAL FIXED ASSETS | C127: 50270 | D127: 50270 | E127: 50270 | F127: 50270 | G127: 50270 | H127: 50270 | I127: 139365 | J127: 50270 | K127: 50270 | L127: 25270
B128: including: short term | C128: 0 | D128: 0 | E128: 0 | F128: 0 | G128: 0 | H128: 0 | I128: 0 | J128: n.a. | K128: n.a. | L128: n.a.
B129: B.III.1. Total equity investments | C129: 50270 | D129: 50270 | E129: 50270 | F129: 50270 | G129: 50270 | H129: 50270 | I129: 139365 | J129: n.a. | K129: n.a. | L129: n.a.
B130: B.III.1.a. Subsidiary companies | C130: 50000 | D130: 50000 | E130: 50000 | F130: 50000 | G130: 50000 | H130: 50000 | I130: 139095 | J130: n.a. | K130: n.a. | L130: n.a.
B131: B.III.1.b. Associated companies | C131: 0 | D131: 0 | E131: 0 | F131: 0 | G131: 0 | H131: 0 | I131: 0 | J131: n.a. | K131: n.a. | L131: n.a.
B132: B.III.1.c. Parent companies | C132: 0 | D132: 0 | E132: 0 | F132: 0 | G132: 0 | H132: 0 | I132: 0 | J132: n.a. | K132: n.a. | L132: n.a.
B133: B.III.1.d. Companies under parent companies control | C133: 0 | D133: 0 | E133: 0 | F133: 0 | G133: 0 | H133: 0 | I133: 0 | J133: n.a. | K133: n.a. | L133: n.a.
B134: B.III.1.d.bis. Other companies | C134: 270 | D134: 270 | E134: 270 | F134: 270 | G134: 270 | H134: 270 | I134: 270 | J134: n.a. | K134: n.a. | L134: n.a.
B135: B.III.2. Total Receivables | C135: 0 | D135: 0 | E135: 0 | F135: 0 | G135: 0 | H135: 0 | I135: 0 | J135: n.a. | K135: n.a. | L135: 0
B136: B.III.2.a. Due from subsidiary comp. | C136: 0 | D136: 0 | E136: 0 | F136: 0 | G136: 0 | H136: 0 | I136: 0 | J136: n.a. | K136: n.a. | L136: 0
B137: B.III.2.a. Due from subs. comp. - beyond 12 months | C137: 0 | D137: 0 | E137: 0 | F137: 0 | G137: 0 | H137: 0 | I137: 0 | J137: n.a. | K137: n.a. | L137: 0
B138: B.III.2.b. Due from assoc. comp. | C138: 0 | D138: 0 | E138: 0 | F138: 0 | G138: 0 | H138: 0 | I138: 0 | J138: n.a. | K138: n.a. | L138: 0
B139: B.III.2.b. Due from assoc. comp. - beyond 12 months | C139: 0 | D139: 0 | E139: 0 | F139: 0 | G139: 0 | H139: 0 | I139: 0 | J139: n.a. | K139: n.a. | L139: 0
B140: B.III.2.c. Due from parent comp. | C140: 0 | D140: 0 | E140: 0 | F140: 0 | G140: 0 | H140: 0 | I140: 0 | J140: n.a. | K140: n.a. | L140: 0
B141: B.III.2.c. Due from parent comp. - beyond 12 months | C141: 0 | D141: 0 | E141: 0 | F141: 0 | G141: 0 | H141: 0 | I141: 0 | J141: n.a. | K141: n.a. | L141: 0
B142: B.III.2.d. Due from comp. under parent companies control | C142: 0 | D142: 0 | E142: 0 | F142: 0 | G142: 0 | H142: 0 | I142: 0 | J142: n.a. | K142: n.a. | L142: n.a.
B143: B.III.2.d. Due from comp. under parent companies control - beyond 12 months | C143: 0 | D143: 0 | E143: 0 | F143: 0 | G143: 0 | H143: 0 | I143: 0 | J143: n.a. | K143: n.a. | L143: n.a.
...

Sheet Balance sheet
A1: Balance sheet
A3: Unconsolidated | B3: 31/03/2020 EUR | C3: 31/03/2021 EUR | D3: 31/03/2022 EUR | E3: 31/03/2023 EUR | F3: 31/03/2024 EUR
B4: 12 months Detailed ICS | C4: 12 months Detailed ICS | D4: 12 months Detailed ICS | E4: 12 months Detailed ICS | F4: 12 months Detailed ICS
A5: Assets
A6: A. TOTAL receivables due from shareholders | B6: 0 | C6: 0 | D6: 0 | E6: 0 | F6: 0
A7: Called share capital | B7: 0 | C7: 0 | D7: 0 | E7: 0 | F7: 0
A9: B. TOTAL FIXED ASSETS | B9: 577699 | C9: 563008 | D9: 836581 | E9: 1533059 | F9: 1597153
A10: B.I. TOTAL INTANGIBLE FIXED ASSETS | B10: 412309 | C10: 348629 | D10: 494303 | E10: 1141024 | F10: 947984
A11: B.I.1. Start-up and expansion costs | B11: 0 | C11: 0 | D11: 0 | E11: 0 | F11: 0
A12: B.I.2. Research and dev. exp. | B12: 0 | C12: 0 | D12: 0 | E12: 0 | F12: 0
A13: B.I.3. Ind. patents and intellect. property rights | B13: 2500 | C13: 7776 | D13: 0 | E13: 502430 | F13: 378595
A14: B.I.4. Concessions, licenses, trademarks and similar rights | B14: 22091 | C14: 24644 | D14: 23054 | E14: 30220 | F14: 31737
A15: B.I.5. Goodwill/Consolidation Difference | B15: 2059 | C15: 1625 | D15: 1190 | E15: 755 | F15: 320
A16: including: Goodwill | B16: 2059 | C16: 1625 | D16: 1190 | E16: 755 | F16: 320
A17: B.I.6. Additions in progress and advances | B17: 0 | C17: 0 | D17: 0 | E17: 0 | F17: 0
A18: B.I.7. Others | B18: 385659 | C18: 314584 | D18: 470059 | E18: 607619 | F18: 537332
A19: (Amortization provision) | B19: n.a. | C19: n.a. | D19: n.a. | E19: n.a. | F19: n.a.
A21: B.II. TOTAL TANGIBLE FIXED ASSETS | B21: 115120 | C21: 164109 | D21: 292008 | E21: 341765 | F21: 598899
A22: including: leased tangible assets | B22: n.a. | C22: n.a. | D22: n.a. | E22: n.a. | F22: n.a.
A23: B.II.1. Land and buildings | B23: 0 | C23: 0 | D23: 0 | E23: 0 | F23: 0
A24: B.II.2. Plant and machinery | B24: 0 | C24: 0 | D24: 0 | E24: 0 | F24: 0
A25: B.II.3. Indust. and commercial equipment | B25: 97013 | C25: 103437 | D25: 271989 | E25: 315454 | F25: 473049
A26: B.II.4. Other assets | B26: 18107 | C26: 60672 | D26: 20019 | E26: 26311 | F26: 125850
A27: B.II.5. Additions in progress and advances | B27: 0 | C27: 0 | D27: 0 | E27: 0 | F27: 0
A28: (Depreciation provision) | B28: n.a. | C28: n.a. | D28: n.a. | E28: n.a. | F28: n.a.
A30: B.III. TOTAL FINANCIAL FIXED ASSETS | B30: 50270 | C30: 50270 | D30: 50270 | E30: 50270 | F30: 50270
A31: including: short term | B31: 0 | C31: 0 | D31: 0 | E31: 0 | F31: 0
A32: B.III.1. Total equity investments | B32: 50270 | C32: 50270 | D32: 50270 | E32: 50270 | F32: 50270
A33: B.III.1.a. Subsidiary companies | B33: 50000 | C33: 50000 | D33: 50000 | E33: 50000 | F33: 50000
A34: B.III.1.b. Associated companies | B34: 0 | C34: 0 | D34: 0 | E34: 0 | F34: 0
A35: B.III.1.c. Parent companies | B35: 0 | C35: 0 | D35: 0 | E35: 0 | F35: 0
A36: B.III.1.d. Companies under parent companies control | B36: 0 | C36: 0 | D36: 0 | E36: 0 | F36: 0
A37: B.III.1.d.bis. Other companies | B37: 270 | C37: 270 | D37: 270 | E37: 270 | F37: 270
A38: B.III.2. Total Receivables | B38: 0 | C38: 0 | D38: 0 | E38: 0 | F38: 0
A39: B.III.2.a. Due from subsidiary comp. | B39: 0 | C39: 0 | D39: 0 | E39: 0 | F39: 0
A40: B.III.2.a. Due from subs. comp. - beyond 12 months | B40: 0 | C40: 0 | D40: 0 | E40: 0 | F40: 0
A41: B.III.2.b. Due from assoc. comp. | B41: 0 | C41: 0 | D41: 0 | E41: 0 | F41: 0
... A82: C.II. RECEIV. DUE WITHIN 12 MONTHS | B82: 3697489 | C82: 3520108 | D82: 5456367 | E82: 5081312 | F82: 6368430
A83: Amounts due for advance taxation | B83: n.a. | C83: n.a. | D83: n.a. | E83: n.a. | F83: n.a.
A84: C.II. RECEIV. DUE BEYOND 12 MONTHS | B84: 0 | C84: 0 | D84: 0 | E84: 0 | F84: 0
A86: C.III. TOTAL FINANCIAL ASSETS | B86: 0 | C86: 0 | D86: 0 | E86: 0 | F86: 0
A87: C.III.1. Invest. in subs. comp. | B87: 0 | C87: 0 | D87: 0 | E87: 0 | F87: 0
A88: C.III.2. Invest. in assoc. comp. | B88: 0 | C88: 0 | D88: 0 | E88: 0 | F88: 0
A89: C.III.3. Invest. in parent comp. | B89: 0 | C89: 0 | D89: 0 | E89: 0 | F89: 0
A90: C.III.3.bis. Invest. in comp. under parent companies control | B90: 0 | C90: 0 | D90: 0 | E90: 0 | F90: 0
A91: C.III.4. Other investments | B91: 0 | C91: 0 | D91: 0 | E91: 0 | F91: 0
A92: C.III.4.bis. Own shares | B92: 0 | C92: 0 | D92: 0 | E92: 0 | F92: 0
A93: Own shares: par value | B93: 0 | C93: 0 | D93: 0 | E93: 0 | F93: 0
A94: C.III.5. Derivatives | B94: 0 | C94: 0 | D94: 0 | E94: 0 | F94: 0
A95: C.III.6. Other securities | B95: 0 | C95: 0 | D95: 0 | E95: 0 | F95: 0
A96: C.III.7. Financial instruments for cash pooling | B96: 0 | C96: 0 | D96: 0 | E96: 0 | F96: 0
... A103: D. TOTAL ACCRUED INCOME AND PREPAID EXPENSES | B103: 1239211 | C103: 848040 | D103: 449103 | E103: 708330 | F103: 637766
A104: Accrued income and prepaid exp. | B104: n.a. | C104: n.a. | D104: n.a. | E104: n.a. | F104: n.a.
A106: TOTAL ASSETS | B106: 6831833 | C106: 7250567 | D106: 8985482 | E106: 10877098 | F106: 11990730
A108: Liabilities
A110: Shareholders' funds
A112: A. TOTAL SHAREHOLDERS' FUNDS | B112: 662137 | C112: 966890 | D112: 1480696 | E112: 2257478 | F112: 2929765
A113: A.I. Capital stock | B113: 100000 | C113: 100000 | D113: 100000 | E113: 100000 | F113: 100000
A114: including: Prepaid call from shareholders | B114: 0 | C114: 0 | D114: 0 | E114: 0 | F114: 0
A115: including: Deposits for future capital increase | B115: 0 | C115: 0 | D115: 0 | E115: 0 | F115: 0
A116: including: Deposits for capital | B116: 0 | C116: 0 | D116: 0 | E116: 0 | F116: 0
A117: including: Deposits for loss covering | B117: 0 | C117: 0 | D117: 0 | E117: 0 | F117: 0
A118: A.II. Share premium reserve | B118: 0 | C118: 0 | D118: 0 | E118: 0 | F118: 0
A119: A.III. Revaluation reserves | B119: 0 | C119: 0 | D119: 0 | E119: 0 | F119: 0
A120: A.IV. Legal reserve | B120: 2000 | C120: 2000 | D120: 2000 | E120: 2000 | F120: 2000
A121: A.V. Statutory reserves | B121: 0 | C121: 0 | D121: 0 | E121: 0 | F121: 0
A122: Reserve for treasury stock | B122: 0 | C122: 0 | D122: 0 | E122: 0 | F122: 0
A123: A.VI. Other reserves | B123: 540433 | C123: 540436 | D123: 540434 | E123: 540436 | F123: 540433
A124: GROUP consolidation reserve | B124: n.a. | C124: n.a. | D124: n.a. | E124: n.a. | F124: n.a.
A125: A.VII. Reserve for expected cash flow hedge | B125: 0 | C125: 0 | D125: 0 | E125: 0 | F125: 0
A126: A.VIII. Retained earnings (losses) | B126: 0 | C126: 19704 | D126: 324454 | E126: 838262 | F126: 1615043
A127: A.IX. Profit (loss) for the year | B127: 19704 | C127: 304750 | D127: 513808 | E127: 776780 | F127: 672289
A128: Dividend down payment | B128: 0 | C128: 0 | D128: 0 | E128: 0 | F128: 0
A129: Partial covering for loss of the year | B129: 0 | C129: 0 | D129: 0 | E129: 0 | F129: 0
A130: A.X. Negative reserves for own shares (+/-) | B130: 0 | C130: 0 | D130: 0 | E130: 0 | F130: 0
A131: Group capital stock and reserves | B131: n.a. | C131: n.a. | D131: n.a. | E131: n.a. | F131: n.a.
A132: Minority interests in cap. and reserves | B132: n.a. | C132: n.a. | D132: n.a. | E132: n.a. | F132: n.a.
A133: including: deferred taxes | B133: 0 | C133: 0 | D133: 0 | E133: 0 | F133: 0
A134: Minority interests in profit (loss) for the year | B134: n.a. | C134: n.a. | D134: n.a. | E134: n.a. | F134: n.a.
A135: MINORITY INTERESTS SHAREHOLDERS' FUNDS | B135: n.a. | C135: n.a. | D135: n.a. | E135: n.a. | F135: n.a.
A137: B. TOTAL PROVISIONS FOR RISKS AND CHARGES | B137: 0 | C137: 0 | D137: 0 | E137: 0 | F137: 0
A138: B.1. Employee pensions and similar obligations | B138: 0 | C138: 0 | D138: 0 | E138: 0 | F138: 0
A139: B.2. Taxation (including deferred taxation) | B139: 0 | C139: 0 | D139: 0 | E139: 0 | F139: 0
A140: B.3. Derivative liabilities | B140: 0 | C140: 0 | D140: 0 | E140: 0 | F140: 0
A141: B.4. Other provisions | B141: 0 | C141: 0 | D141: 0 | E141: 0 | F141: 0
A142: of which: consolidation provision | B142: n.a. | C142: n.a. | D142: n.a. | E142: n.a. | F142: n.a.
A144: C. SEVERANCE INDEMNITY RESERVE | B144: 193620 | C144: 220634 | D144: 253701 | E144: 307482 | F144: 275626
A146: Payables
A148: D. TOTAL PAYABLES | B148: 5813222 | C148: 5876201 | D148: 7028521 | E148: 8006873 | F148: 8468346
A149: D.1. Bonds | B149: 0 | C149: 0 | D149: 0 | E149: 0 | F149: 0
A150: D.1. Bonds beyond 12 months | B150: 0 | C150: 0 | D150: 0 | E150: 0 | F150: 0 | J150: x
A151: D.2. Convertible bonds | B151: 0 | C151: 0 | D151: 0 | E151: 0 | F151: 0
A152: D.2. Convertible bonds - beyond 12 months | B152: 0 | C152: 0 | D152: 0 | E152: 0 | F152: 0 | J152: x
A153: D.3. Due to shareholders for loans | B153: 0 | C153: 0 | D153: 0 | E153: 0 | F153: 0
A154: D.3. Due to shareholders for loans - beyond 12 months | B154: 1300000 | C154: 1300000 | D154: 0 | E154: 0 | F154: 0 | J154: x
A155: D.4. Due to banks | B155: 954402 | C155: 408353 | D155: 1174483 | E155: 893797 | F155: 2067585
A156: D.4. Due to banks - beyond 12 months | B156: 1967673 | C156: 2590830 | D156: 2014910 | E156: 3256605 | F156: 3190619 | J156: x
A157: D.5. Due to other lenders | B157: 0 | C157: 0 | D157: 0 | E157: 0 | F157: 0
A158: D.5. Due to other lenders - beyond 12 months | B158: 0 | C158: 0 | D158: 1300000 | E158: 1226527 | F158: 1052935 | J158: x
A159: D.6. Advances | B159: 0 | C159: 0 | D159: 0 | E159: 0 | F159: 0
...

Sheet Original statements
B1: LUIS T. - S.R.L.
A4: 39100 Bolzano | B4: Tax code | C4: 02274840210
B5: CCIAA number | C5: BZ0167343
A6: Private company
A7: The Global Ultimate Owner of this controlled subsidiary is MR MARKUS BAUMGARTNER
A10: Contact details
A13: Registered office address
A14: WERNER-VON-SIEMENS-STRASSE, 18 | B14: Phone number | C14: 0471095564
A15: 39100 Bolzano | B15: Website address | C15: =HYPERLINK("http://www.luistrenker.com/","www.luistrenker.com") -> www.luistrenker.com
A16: BOLZANO/BOZEN(TRENTINO-ALTO ADIGE/SÜDTIROL)
A18: Trading address
A19: VIA VON SIEMENS 18 | B19: Phone number | C19: 0471095564
A20: 39100 Bolzano
A21: BOLZANO/BOZEN(TRENTINO-ALTO ADIGE)
A24: Legal & account information
A27: Previous name
A28: 08/2012 | B28: LUIS T. - S.R.L. % LUIS T. G.M.B.H.
A29: The date of name change has no legal validity but is the date BvD detected the name change
A31: Legal status | B31: Active | C31: Last accounting closing date | D31: 31/03/2025
A32: Legal form | B32: Limited liability company - SRL
C33: No of available years | D33: 10
A34: Date of incorporation | B34: 37077 | C34: Available accounts | D34: Unconsolidated
C35: Last accounting model | D35: Detailed
A38: Size and group information
A41: Turnover (2025) | B41: 14.885.328 EUR | C41: BvD independence indicator | D41: D
A42: Profit (loss) (2025) | B42: 160.035 EUR
C43: No of companies in corporate group | D43: 7
A44: Total assets (2025) | B44: 12.930.506 EUR
A45: Employees (2025) | B45: 52
C46: No of recorded shareholders | D46: 4
A47: Social capital (2025) | B47: 100 th EUR
C49: No of recorded subsidiaries | D49: 2
A51: Main exchange | B51: Unlisted
A54: Industry classification
A57: Italian trade description | B57: CONFEZIONE DI ARTICOLI DI ABBIGLIAMENTO (ESCLUSO ABBIGLIAMENTO IN LLICCIA)
A59: Ateco 2007 code | B59: 141000 Manufacture of wearing apparel, except fur apparel
A61: SAE code | B61: 430 Imprese produttive
A63: RAE code | B63: 453 Articoli di abbigliamento ed accessori
A66: Peer group
A69: Name | B69: 141 VL (Very large companies)
A70: Description | B70: Confezione di articoli di abbigliamento (escluso abbligliamento in pelliccia)
A71: Size | B71: 1.742 companies
A74: Key financials & employees
B76: Unconsolidated | C76: 31/03/2025 EUR | D76: 31/03/2024 EUR | E76: 31/03/2023 EUR | F76: 31/03/2022 EUR | G76: 31/03/2021 EUR | H76: 31/03/2020 EUR | I76: 31/03/2019 EUR | J76: 31/03/2018 EUR | K76: 31/03/2017 EUR | L76: 31/03/2016 EUR
C77: 12 months Detailed ICS | D77: 12 months Detailed ICS | E77: 12 months Detailed ICS | F77: 12 months Detailed ICS | G77: 12 months Detailed ICS | H77: 12 months Detailed ICS | I77: 12 months Detailed ICS | J77: 12 months Abbreviated (D) ICS | K77: 12 months Abbreviated (D) ICS | L77: 12 months Abbreviated (D) ICS
B79: Revenues from sales and services | C79: 14885328 | D79: 14294364 | E79: 13782014 | F79: 11619465 | G79: 8552816 | H79: 9712939 | I79: 10220941 | J79: 8912701 | K79: 7807091 | L79: 6287625
B80: EBITDA | C80: 1062376 | D80: 1513067 | E80: 1608701 | F80: 1473280 | G80: 889518 | H80: 701754 | I80: 595594 | J80: 670640 | K80: 532113 | L80: 445108
B81: Profit (loss) | C81: 160035 | D81: 672289 | E81: 776780 | F81: 513808 | G81: 304750 | H81: 19704 | I81: 209448 | J81: 256820 | K81: 164166 | L81: 124157
B82: Total assets | C82: 12930506 | D82: 11990730 | E82: 10877098 | F82: 8985482 | G82: 7250567 | H82: 6831833 | I82: 7194117 | J82: 5269792 | K82: 4342288 | L82: 4392744
B83: Total shareholder's funds | C83: 3089801 | D83: 2929765 | E83: 2257478 | F83: 1480696 | G83: 966890 | H83: 662137 | I83: 642433 | J83: 432985 | K83: 176166 | L83: 320323
B84: Net financial position | C84: 5455097 | D84: 5886637 | E84: 4714792 | F84: 4399459 | G84: 2565050 | H84: 2849112 | I84: 3938981 | J84: 1176954 | K84: 749968 | L84: 862739
B86: EBITDA/vendite (%) | C86: 6.9 | D86: 10.12 | E86: 11.12 | F86: 11.64 | G86: 9.62 | H86: 6.64 | I86: 5.59 | J86: 7.24 | K86: 6.57 | L86: 6.83
B87: Return on sales (ROS) (%) | C87: 3.56 | D87: 7.4 | E87: 8.68 | F87: 7.02 | G87: 5.92 | H87: 2.92 | I87: 4.56 | J87: 5.89 | K87: 5.43 | L87: 5.49
B88: Return on asset (ROA) (%) | C88: 4.24 | D88: 9.23 | E88: 11.54 | F88: 9.89 | G88: 7.54 | H88: 4.52 | I88: 6.75 | J88: 10.35 | K88: 10.12 | L88: 8.15
B89: Return on equity (ROE) (%) | C89: 5.18 | D89: 22.95 | E89: 34.41 | F89: 34.7 | G89: 31.52 | H89: 2.98 | I89: 32.6 | J89: 59.31 | K89: 93.19 | L89: 38.76
B90: Debt/equity ratio | C90: 2.16 | D90: 2.15 | E90: 2.38 | F90: 3.03 | G90: 3.1 | H90: 4.41 | I90: 6.2 | J90: 2.88 | K90: 4.44 | L90: 2.76
B91: Banks/turnover (%) | C91: 36.49 | D91: 35.17 | E91: 28.68 | F91: 25.19 | G91: 32.45 | H91: 27.67 | I91: 25.15 | J91: 13.44 | K91: 9.66 | L91: 13.55
... B95: Number of employees | C95: 52 | D95: 48 | E95: 42 | F95: 40 | G95: 38 | H95: 36 | I95: 25 | J95: 19 | K95: 15 | L95: 15
A98: Balance sheet
B100: Unconsolidated | C100: 31/03/2025 EUR | D100: 31/03/2024 EUR | E100: 31/03/2023 EUR | F100: 31/03/2022 EUR | G100: 31/03/2021 EUR | H100: 31/03/2020 EUR | I100: 31/03/2019 EUR | J100: 31/03/2018 EUR | K100: 31/03/2017 EUR | L100: 31/03/2016 EUR
C101: 12 months Detailed ICS | D101: 12 months Detailed ICS | E101: 12 months Detailed ICS | F101: 12 months Detailed ICS | G101: 12 months Detailed ICS | H101: 12 months Detailed ICS | I101: 12 months Detailed ICS | J101: 12 months Abbreviated (D) ICS | K101: 12 months Abbreviated (D) ICS | L101: 12 months Abbreviated (D) ICS
B102: Assets
B103: A. TOTAL receivables due from shareholders | C103: 0 | D103: 0 | E103: 0 | F103: 0 | G103: 0 | H103: 0 | I103: 0 | J103: 0 | K103: 0 | L103: 0
B104: Called share capital | C104: 0 | D104: 0 | E104: 0 | F104: 0 | G104: 0 | H104: 0 | I104: 0 | J104: 0 | K104: 0 | L104: 0
B106: B. TOTAL FIXED ASSETS | C106: 2157604 | D106: 1597153 | E106: 1533059 | F106: 836581 | G106: 563008 | H106: 577699 | I106: 692542 | J106: 644223 | K106: 276336 | L106: 303839
B107: B.I. TOTAL INTANGIBLE FIXED ASSETS | C107: 1446204 | D107: 947984 | E107: 1141024 | F107: 494303 | G107: 348629 | H107: 412309 | I107: 438786 | J107: 470038 | K107: 82026 | L107: 117794
B108: B.I.1. Start-up and expansion costs | C108: 0 | D108: 0 | E108: 0 | F108: 0 | G108: 0 | H108: 0 | I108: 0 | J108: n.a. | K108: n.a. | L108: n.a.
B109: B.I.2. Research and dev. exp. | C109: 0 | D109: 0 | E109: 0 | F109: 0 | G109: 0 | H109: 0 | I109: 0 | J109: n.a. | K109: n.a. | L109: n.a.
B110: B.I.3. Ind. patents and intellect. property rights | C110: 457183 | D110: 378595 | E110: 502430 | F110: 0 | G110: 7776 | H110: 2500 | I110: 8000 | J110: n.a. | K110: n.a. | L110: n.a.
B111: B.I.4. Concessions, licenses, trademarks and similar rights | C111: 303484 | D111: 31737 | E111: 30220 | F111: 23054 | G111: 24644 | H111: 22091 | I111: 18364 | J111: n.a. | K111: n.a. | L111: n.a.
B112: B.I.5. Goodwill/Consolidation Difference | C112: 0 | D112: 320 | E112: 755 | F112: 1190 | G112: 1625 | H112: 2059 | I112: 2494 | J112: n.a. | K112: n.a. | L112: n.a.
B113: including: Goodwill | C113: 0 | D113: 320 | E113: 755 | F113: 1190 | G113: 1625 | H113: 2059 | I113: 2494 | J113: n.a. | K113: n.a. | L113: n.a.
B114: B.I.6. Additions in progress and advances | C114: 0 | D114: 0 | E114: 0 | F114: 0 | G114: 0 | H114: 0 | I114: 0 | J114: n.a. | K114: n.a. | L114: n.a.
B115: B.I.7. Others | C115: 685537 | D115: 537332 | E115: 607619 | F115: 470059 | G115: 314584 | H115: 385659 | I115: 409928 | J115: n.a. | K115: n.a. | L115: n.a.
B116: (Amortization provision) | C116: n.a. | D116: n.a. | E116: n.a. | F116: n.a. | G116: n.a. | H116: n.a. | I116: n.a. | J116: 637202 | K116: 560857 | L116: 516308
B118: B.II. TOTAL TANGIBLE FIXED ASSETS | C118: 661130 | D118: 598899 | E118: 341765 | F118: 292008 | G118: 164109 | H118: 115120 | I118: 114391 | J118: 123915 | K118: 144040 | L118: 160775
B119: including: leased tangible assets | C119: n.a. | D119: n.a. | E119: n.a. | F119: n.a. | G119: n.a. | H119: n.a. | I119: n.a. | J119: n.a. | K119: n.a. | L119: n.a.
B120: B.II.1. Land and buildings | C120: 0 | D120: 0 | E120: 0 | F120: 0 | G120: 0 | H120: 0 | I120: 0 | J120: n.a. | K120: n.a. | L120: n.a.
B121: B.II.2. Plant and machinery | C121: 0 | D121: 0 | E121: 0 | F121: 0 | G121: 0 | H121: 0 | I121: 0 | J121: n.a. | K121: n.a. | L121: n.a.
B122: B.II.3. Indust. and commercial equipment | C122: 566644 | D122: 473049 | E122: 315454 | F122: 271989 | G122: 103437 | H122: 97013 | I122: 89836 | J122: n.a. | K122: n.a. | L122: n.a.
B123: B.II.4. Other assets | C123: 94486 | D123: 125850 | E123: 26311 | F123: 20019 | G123: 60672 | H123: 18107 | I123: 24555 | J123: n.a. | K123: n.a. | L123: n.a.
B124: B.II.5. Additions in progress and advances | C124: 0 | D124: 0 | E124: 0 | F124: 0 | G124: 0 | H124: 0 | I124: 0 | J124: n.a. | K124: n.a. | L124: n.a.
B125: (Depreciation provision) | C125: n.a. | D125: n.a. | E125: n.a. | F125: n.a. | G125: n.a. | H125: n.a. | I125: n.a. | J125: 341146 | K125: 293996 | L125: 245698
B127: B.III. TOTAL FINANCIAL FIXED ASSETS | C127: 50270 | D127: 50270 | E127: 50270 | F127: 50270 | G127: 50270 | H127: 50270 | I127: 139365 | J127: 50270 | K127: 50270 | L127: 25270
B128: including: short term | C128: 0 | D128: 0 | E128: 0 | F128: 0 | G128: 0 | H128: 0 | I128: 0 | J128: n.a. | K128: n.a. | L128: n.a.
B129: B.III.1. Total equity investments | C129: 50270 | D129: 50270 | E129: 50270 | F129: 50270 | G129: 50270 | H129: 50270 | I129: 139365 | J129: n.a. | K129: n.a. | L129: n.a.
B130: B.III.1.a. Subsidiary companies | C130: 50000 | D130: 50000 | E130: 50000 | F130: 50000 | G130: 50000 | H130: 50000 | I130: 139095 | J130: n.a. | K130: n.a. | L130: n.a.
B131: B.III.1.b. Associated companies | C131: 0 | D131: 0 | E131: 0 | F131: 0 | G131: 0 | H131: 0 | I131: 0 | J131: n.a. | K131: n.a. | L131: n.a.
B132: B.III.1.c. Parent companies | C132: 0 | D132: 0 | E132: 0 | F132: 0 | G132: 0 | H132: 0 | I132: 0 | J132: n.a. | K132: n.a. | L132: n.a.
B133: B.III.1.d. Companies under parent companies control | C133: 0 | D133: 0 | E133: 0 | F133: 0 | G133: 0 | H133: 0 | I133: 0 | J133: n.a. | K133: n.a. | L133: n.a.
B134: B.III.1.d.bis. Other companies | C134: 270 | D134: 270 | E134: 270 | F134: 270 | G134: 270 | H134: 270 | I134: 270 | J134: n.a. | K134: n.a. | L134: n.a.
B135: B.III.2. Total Receivables | C135: 0 | D135: 0 | E135: 0 | F135: 0 | G135: 0 | H135: 0 | I135: 0 | J135: n.a. | K135: n.a. | L135: 0
B136: B.III.2.a. Due from subsidiary comp. | C136: 0 | D136: 0 | E136: 0 | F136: 0 | G136: 0 | H136: 0 | I136: 0 | J136: n.a. | K136: n.a. | L136: 0
B137: B.III.2.a. Due from subs. comp. - beyond 12 months | C137: 0 | D137: 0 | E137: 0 | F137: 0 | G137: 0 | H137: 0 | I137: 0 | J137: n.a. | K137: n.a. | L137: 0
B138: B.III.2.b. Due from assoc. comp. | C138: 0 | D138: 0 | E138: 0 | F138: 0 | G138: 0 | H138: 0 | I138: 0 | J138: n.a. | K138: n.a. | L138: 0
B139: B.III.2.b. Due from assoc. comp. - beyond 12 months | C139: 0 | D139: 0 | E139: 0 | F139: 0 | G139: 0 | H139: 0 | I139: 0 | J139: n.a. | K139: n.a. | L139: 0
B140: B.III.2.c. Due from parent comp. | C140: 0 | D140: 0 | E140: 0 | F140: 0 | G140: 0 | H140: 0 | I140: 0 | J140: n.a. | K140: n.a. | L140: 0
B141: B.III.2.c. Due from parent comp. - beyond 12 months | C141: 0 | D141: 0 | E141: 0 | F141: 0 | G141: 0 | H141: 0 | I141: 0 | J141: n.a. | K141: n.a. | L141: 0
B142: B.III.2.d. Due from comp. under parent companies control | C142: 0 | D142: 0 | E142: 0 | F142: 0 | G142: 0 | H142: 0 | I142: 0 | J142: n.a. | K142: n.a. | L142: n.a.
B143: B.III.2.d. Due from comp. under parent companies control - beyond 12 months | C143: 0 | D143: 0 | E143: 0 | F143: 0 | G143: 0 | H143: 0 | I143: 0 | J143: n.a. | K143: n.a. | L143: n.a.
...

Sheet Reformulated balance sheet
B1: Table 1.e
B3: Luis Trenker S.r.l.
B4: CONSOLIDATED BALANCE SHEET
C5: 2020 | D5: 2021 | E5: 2022 | F5: 2023 | G5: 2024
B6: (in Euro million)
B7: ASSETS
B8: Non-current assets
B9: Concessions | C9: ='Balance sheet'!B14 -> 22091 | D9: ='Balance sheet'!C14 -> 24644 | E9: ='Balance sheet'!D14 -> 23054 | F9: ='Balance sheet'!E14 -> 30220 | G9: ='Balance sheet'!F14 -> 31737
B10: Goodwill | C10: ='Balance sheet'!B15 -> 2059 | D10: ='Balance sheet'!C15 -> 1625 | E10: ='Balance sheet'!D15 -> 1190 | F10: ='Balance sheet'!E15 -> 755 | G10: ='Balance sheet'!F15 -> 320
B11: Other intangible assets | C11: ='Balance sheet'!B11+'Balance sheet'!B12+'Balance sheet'!B17+'Balance sheet'!B18+'Balance sheet'!B13 -> 388159 | D11: ='Balance sheet'!C11+'Balance sheet'!C12+'Balance sheet'!C17+'Balance sheet'!C18+'Balance sheet'!C13 -> 322360 | E11: ='Balance sheet'!D11+'Balance sheet'!D12+'Balance sheet'!D17+'Balance sheet'!D18+'Balance sheet'!D13 -> 470059 | F11: ='Balance sheet'!E11+'Balance sheet'!E12+'Balance sheet'!E17+'Balance sheet'!E18+'Balance sheet'!E13 -> 1110049 | G11: ='Balance sheet'!F11+'Balance sheet'!F12+'Balance sheet'!F17+'Balance sheet'!F18+'Balance sheet'!F13 -> 915927
B12: Tangible fixed assets | C12: =SUM('Balance sheet'!B23:B27) -> 115120 | D12: =SUM('Balance sheet'!C23:C27) -> 164109 | E12: =SUM('Balance sheet'!D23:D27) -> 292008 | F12: =SUM('Balance sheet'!E23:E27) -> 341765 | G12: =SUM('Balance sheet'!F23:F27) -> 598899
B13: Investments | C13: ='Balance sheet'!B30 -> 50270 | D13: ='Balance sheet'!C30 -> 50270 | E13: ='Balance sheet'!D30 -> 50270 | F13: ='Balance sheet'!E30 -> 50270 | G13: ='Balance sheet'!F30 -> 50270
B14: Deferred tax assets | C14: 0 | D14: 0 | E14: 0 | F14: 0 | G14: 0
B15: Other non-current receivables and financial assets | C15: ='Balance sheet'!B67+'Balance sheet'!B69+'Balance sheet'!B71+'Balance sheet'!B73+'Balance sheet'!B75+'Balance sheet'!B77+'Balance sheet'!B79+'Balance sheet'!B81 -> 0 | D15: ='Balance sheet'!C67+'Balance sheet'!C69+'Balance sheet'!C71+'Balance sheet'!C73+'Balance sheet'!C75+'Balance sheet'!C77+'Balance sheet'!C79+'Balance sheet'!C81 -> 0 | E15: ='Balance sheet'!D67+'Balance sheet'!D69+'Balance sheet'!D71+'Balance sheet'!D73+'Balance sheet'!D75+'Balance sheet'!D77+'Balance sheet'!D79+'Balance sheet'!D81 -> 0 | F15: ='Balance sheet'!E67+'Balance sheet'!E69+'Balance sheet'!E71+'Balance sheet'!E73+'Balance sheet'!E75+'Balance sheet'!E77+'Balance sheet'!E79+'Balance sheet'!E81 -> 0 | G15: ='Balance sheet'!F67+'Balance sheet'!F69+'Balance sheet'!F71+'Balance sheet'!F73+'Balance sheet'!F75+'Balance sheet'!F77+'Balance sheet'!F79+'Balance sheet'!F81 -> 0
B16: Total non-current assets | C16: =SUM(C9:C15) -> 577699 | D16: =SUM(D9:D15) -> 563008 | E16: =SUM(E9:E15) -> 836581 | F16: =SUM(F9:F15) -> 1533059 | G16: =SUM(G9:G15) -> 1597153
B17: Current assets
B18: Trade receivables | C18: ='Balance sheet'!B82 -> 3697489 | D18: ='Balance sheet'!C82 -> 3520108 | E18: ='Balance sheet'!D82 -> 5456367 | F18: ='Balance sheet'!E82 -> 5081312 | G18: ='Balance sheet'!F82 -> 6368430
B19: Inventories | C19: ='Balance sheet'!B57 -> 1244471 | D19: ='Balance sheet'!C57 -> 1885278 | E19: ='Balance sheet'!D57 -> 2153497 | F19: ='Balance sheet'!E57 -> 2892260 | G19: ='Balance sheet'!F57 -> 2962879
B20: Cash and cash equivalents | C20: ='Balance sheet'!B101 -> 4873 | D20: ='Balance sheet'!C101 -> 6128 | E20: ='Balance sheet'!D101 -> 9204 | F20: ='Balance sheet'!E101 -> 16924 | G20: ='Balance sheet'!F101 -> 29539
B21: Other current assets and financial current assets | C21: ='Balance sheet'!B99+'Balance sheet'!B103 -> 1307301 | D21: ='Balance sheet'!C99+'Balance sheet'!C103 -> 1276045 | E21: ='Balance sheet'!D99+'Balance sheet'!D103 -> 529833 | F21: ='Balance sheet'!E99+'Balance sheet'!E103 -> 1353543 | G21: ='Balance sheet'!F99+'Balance sheet'!F103 -> 1032729
B22: Total current assets | C22: =SUM(C18:C21) -> 6254134 | D22: =SUM(D18:D21) -> 6687559 | E22: =SUM(E18:E21) -> 8148901 | F22: =SUM(F18:F21) -> 9344039 | G22: =SUM(G18:G21) -> 10393577
B23: Assets held for sale and discounting operations
B24: TOTAL ASSETS | C24: =C16+C22 -> 6831833 | D24: =D16+D22 -> 7250567 | E24: =E16+E22 -> 8985482 | F24: =F16+F22 -> 10877098 | G24: =G16+G22 -> 11990730
B25: EQUITY AND LIABILITIES
B26: Equity
B27: Share Capital | C27: ='Balance sheet'!B113 -> 100000 | D27: ='Balance sheet'!C113 -> 100000 | E27: ='Balance sheet'!D113 -> 100000 | F27: ='Balance sheet'!E113 -> 100000 | G27: ='Balance sheet'!F113 -> 100000
B28: Other reserves | C28: ='Balance sheet'!B120+'Balance sheet'!B123 -> 542433 | D28: ='Balance sheet'!C120+'Balance sheet'!C123 -> 542436 | E28: ='Balance sheet'!D120+'Balance sheet'!D123 -> 542434 | F28: ='Balance sheet'!E120+'Balance sheet'!E123 -> 542436 | G28: ='Balance sheet'!F120+'Balance sheet'!F123 -> 542433
B29: Retained earnings | C29: ='Balance sheet'!B126 -> 0 | D29: ='Balance sheet'!C126 -> 19704 | E29: ='Balance sheet'!D126 -> 324454 | F29: ='Balance sheet'!E126 -> 838262 | G29: ='Balance sheet'!F126 -> 1615043
B30: Group profit (loss) for the period | C30: ='Balance sheet'!B127 -> 19704 | D30: ='Balance sheet'!C127 -> 304750 | E30: ='Balance sheet'!D127 -> 513808 | F30: ='Balance sheet'!E127 -> 776780 | G30: ='Balance sheet'!F127 -> 672289
B31: Total Equity Attributable to Equity Holders of the Parent | C31: =SUM(C27:C30) -> 662137 | D31: =SUM(D27:D30) -> 966890 | E31: =SUM(E27:E30) -> 1480696 | F31: =SUM(F27:F30) -> 2257478 | G31: =SUM(G27:G30) -> 2929765
B32: Non-controlling-interest | C32: 0 | D32: 0 | E32: 0 | F32: 0 | G32: 0
B33: TOTAL CONSOLIDATED EQUITY | C33: =C31 -> 662137 | D33: =D31 -> 966890 | E33: =E31 -> 1480696 | F33: =F31 -> 2257478 | G33: =G31 -> 2929765
B34: Liabilities
B35: Non-current liabilities
B36: Provisions for risks and charges | C36: ='Balance sheet'!B137 -> 0 | D36: ='Balance sheet'!C137 -> 0 | E36: ='Balance sheet'!D137 -> 0 | F36: ='Balance sheet'!E137 -> 0 | G36: ='Balance sheet'!F137 -> 0
B37: Employee benefits | C37: ='Balance sheet'!B144 -> 193620 | D37: ='Balance sheet'!C144 -> 220634 | E37: ='Balance sheet'!D144 -> 253701 | F37: ='Balance sheet'!E144 -> 307482 | G37: ='Balance sheet'!F144 -> 275626
B38: Deferred tax liabilities | C38: 0 | D38: 0 | E38: 0 | F38: 0 | G38: 0
B39: Non-current liabilities to banks and other financial istitutions | C39: ='Balance sheet'!B150+'Balance sheet'!B152+'Balance sheet'!B156+'Balance sheet'!B158+'Balance sheet'!B160+'Balance sheet'!B162+'Balance sheet'!B164+'Balance sheet'!B174+'Balance sheet'!B176+'Balance sheet'!B178 -> 1967673 | D39: ='Balance sheet'!C150+'Balance sheet'!C152+'Balance sheet'!C156+'Balance sheet'!C158+'Balance sheet'!C160+'Balance sheet'!C162+'Balance sheet'!C164+'Balance sheet'!C174+'Balance sheet'!C176+'Balance sheet'!C178 -> 2590830 | E39: ='Balance sheet'!D150+'Balance sheet'!D152+'Balance sheet'!D156+'Balance sheet'!D158+'Balance sheet'!D160+'Balance sheet'!D162+'Balance sheet'!D164+'Balance sheet'!D174+'Balance sheet'!D176+'Balance sheet'!D178 -> 3314910 | F39: ='Balance sheet'!E150+'Balance sheet'!E152+'Balance sheet'!E156+'Balance sheet'!E158+'Balance sheet'!E160+'Balance sheet'!E162+'Balance sheet'!E164+'Balance sheet'!E174+'Balance sheet'!E176+'Balance sheet'!E178 -> 4483132 | G39: ='Balance sheet'!F150+'Balance sheet'!F152+'Balance sheet'!F156+'Balance sheet'!F158+'Balance sheet'!F160+'Balance sheet'!F162+'Balance sheet'!F164+'Balance sheet'!F174+'Balance sheet'!F176+'Balance sheet'!F178 -> 4243554
B40: Other non-current liabilities | C40: ='Balance sheet'!B154 -> 1300000 | D40: ='Balance sheet'!C154 -> 1300000 | E40: ='Balance sheet'!D154 -> 0 | F40: ='Balance sheet'!E154 -> 0 | G40: ='Balance sheet'!F154 -> 0
B41: Total non-current liabilities | C41: =SUM(C36:C40) -> 3461293 | D41: =SUM(D36:D40) -> 4111464 | E41: =SUM(E36:E40) -> 3568611 | F41: =SUM(F36:F40) -> 4790614 | G41: =SUM(G36:G40) -> 4519180
B42: Current liabilities
B43: Trade payables | C43: ='Balance sheet'!B159+'Balance sheet'!B161 -> 1047973 | D43: ='Balance sheet'!C159+'Balance sheet'!C161 -> 1023644 | E43: ='Balance sheet'!D159+'Balance sheet'!D161 -> 1770389 | F43: ='Balance sheet'!E159+'Balance sheet'!E161 -> 1844400 | G43: ='Balance sheet'!F159+'Balance sheet'!F161 -> 1259596
B44: Current liabilities to banks and other financial institutions | C44: ='Balance sheet'!B149+'Balance sheet'!B151+'Balance sheet'!B155 -> 954402 | D44: ='Balance sheet'!C149+'Balance sheet'!C151+'Balance sheet'!C155 -> 408353 | E44: ='Balance sheet'!D149+'Balance sheet'!D151+'Balance sheet'!D155 -> 1174483 | F44: ='Balance sheet'!E149+'Balance sheet'!E151+'Balance sheet'!E155 -> 893797 | G44: ='Balance sheet'!F149+'Balance sheet'!F151+'Balance sheet'!F155 -> 2067585
B45: Current tax payables | C45: ='Balance sheet'!B173 -> 25687 | D45: ='Balance sheet'!C173 -> 43393 | E45: ='Balance sheet'!D173 -> 155494 | F45: ='Balance sheet'!E173 -> 75574 | G45: ='Balance sheet'!F173 -> 105048
B46: Other current liabilities | C46: ='Balance sheet'!B153+'Balance sheet'!B157+'Balance sheet'!B165+'Balance sheet'!B175+'Balance sheet'!B177+'Balance sheet'!B185 -> 680341 | D46: ='Balance sheet'!C153+'Balance sheet'!C157+'Balance sheet'!C165+'Balance sheet'!C175+'Balance sheet'!C177+'Balance sheet'!C185 -> 696823 | E46: ='Balance sheet'!D153+'Balance sheet'!D157+'Balance sheet'!D165+'Balance sheet'!D175+'Balance sheet'!D177+'Balance sheet'!D185 -> 835809 | F46: ='Balance sheet'!E153+'Balance sheet'!E157+'Balance sheet'!E165+'Balance sheet'!E175+'Balance sheet'!E177+'Balance sheet'!E185 -> 1015235 | G46: ='Balance sheet'!F153+'Balance sheet'!F157+'Balance sheet'!F165+'Balance sheet'!F175+'Balance sheet'!F177+'Balance sheet'!F185 -> 1109556
B47: Total current liabilities | C47: =SUM(C43:C46) -> 2708403 | D47: =SUM(D43:D46) -> 2172213 | E47: =SUM(E43:E46) -> 3936175 | F47: =SUM(F43:F46) -> 3829006 | G47: =SUM(G43:G46) -> 4541785
B48: Libilities held for sale and discountiung | C48: 0 | D48: 0 | E48: 0 | F48: 0 | G48: 0
B49: TOTAL LIABILITIES | C49: =C41+C47 -> 6169696 | D49: =D41+D47 -> 6283677 | E49: =E41+E47 -> 7504786 | F49: =F41+F47 -> 8619620 | G49: =G41+G47 -> 9060965
B50: TOTAL LIABILITIES AND EQUITY | C50: =C49+C33 -> 6831833 | D50: =D49+D33 -> 7250567 | E50: =E49+E33 -> 8985482 | F50: =F49+F33 -> 10877098 | G50: =G49+G33 -> 11990730
B53: Luis Trenker S.r.l. | J53: Luis Trenker S.r.l.
B54: REFORMULATED BALANCE SHEET | J54: REFORMULATED BALANCE SHEET | R54: YEAR TO YEAR GROWTH RATES
C55: 2020 | D55: 2021 | E55: 2022 | F55: 2023 | G55: 2024 | K55: 2020 | L55: 2021 | M55: 2022 | N55: 2023 | O55: 2024 | Q55: 2021 | R55: 2022 | S55: 2023 | T55: 2024 | U55: CAGR 2021-2024
B56: (€ millions) | J56: (€ millions)
B57: ASSETS | J57: ASSETS
B58: Operating Assets | J58: Operating Assets
B59: Accounts receivable | C59: ='Balance sheet'!B66+'Balance sheet'!B67 -> 2325766 | D59: ='Balance sheet'!C66+'Balance sheet'!C67 -> 1192500 | E59: ='Balance sheet'!D66+'Balance sheet'!D67 -> 1268047 | F59: ='Balance sheet'!E66+'Balance sheet'!E67 -> 1367114 | G59: ='Balance sheet'!F66+'Balance sheet'!F67 -> 899391 | J59: Accounts receivable | K59: =C59/$C$71 -> 0.34043075 | L59: =D59/$D$71 -> 0.1644699 | M59: =E59/$E$71 -> 0.14112176 | N59: =F59/$F$71 -> 0.12568738 | O59: =G59/$G$71 -> 0.075007193 | Q59: =L59-K59 -> -0.17596085 | R59: =(E59/D59)-1 -> 0.063351782 | S59: =(F59/E59)-1 -> 0.078125653 | T59: =(G59/F59)-1 -> -0.34212436 | U59: =(((G59/D59)^(1/3))-1) -> -0.08974435
B60: Inventories | C60: ='Balance sheet'!B57 -> 1244471 | D60: ='Balance sheet'!C57 -> 1885278 | E60: ='Balance sheet'!D57 -> 2153497 | F60: ='Balance sheet'!E57 -> 2892260 | G60: ='Balance sheet'!F57 -> 2962879 | J60: Inventories | K60: =C60/$C$71 -> 0.1821577 | L60: =D60/$D$71 -> 0.26001801 | M60: =E60/$E$71 -> 0.23966405 | N60: =F60/$F$71 -> 0.26590364 | O60: =G60/$G$71 -> 0.24709747 | Q60: =L60-K60 -> 0.077860308 | R60: =(E60/D60)-1 -> 0.14227026 | S60: =(F60/E60)-1 -> 0.34305272 | T60: =(G60/F60)-1 -> 0.024416546 | U60: =(((G60/D60)^(1/3))-1) -> 0.16264244
B61: Property, plant & equipment | C61: ='Balance sheet'!B21 -> 115120 | D61: ='Balance sheet'!C21 -> 164109 | E61: ='Balance sheet'!D21 -> 292008 | F61: ='Balance sheet'!E21 -> 341765 | G61: ='Balance sheet'!F21 -> 598899 | J61: =B61 -> Property, plant & equipment | K61: =C61/$C$71 -> 0.016850529 | L61: =D61/$D$71 -> 0.022633954 | M61: =E61/$E$71 -> 0.032497756 | N61: =F61/$F$71 -> 0.031420605 | O61: =G61/$G$71 -> 0.049946834 | Q61: =L61-K61 -> 0.005783425 | R61: =(E61/D61)-1 -> 0.77935397 | S61: =(F61/E61)-1 -> 0.17039602 | T61: =(G61/F61)-1 -> 0.75237078 | U61: =(((G61/D61)^(1/3))-1) -> 0.53959702
B62: Other intangible assets | C62: ='Balance sheet'!B11+'Balance sheet'!B12+'Balance sheet'!B13+'Balance sheet'!B14+'Balance sheet'!B17+'Balance sheet'!B18 -> 410250 | D62: ='Balance sheet'!C11+'Balance sheet'!C12+'Balance sheet'!C13+'Balance sheet'!C14+'Balance sheet'!C17+'Balance sheet'!C18 -> 347004 | E62: ='Balance sheet'!D11+'Balance sheet'!D12+'Balance sheet'!D13+'Balance sheet'!D14+'Balance sheet'!D17+'Balance sheet'!D18 -> 493113 | F62: ='Balance sheet'!E11+'Balance sheet'!E12+'Balance sheet'!E13+'Balance sheet'!E14+'Balance sheet'!E17+'Balance sheet'!E18 -> 1140269 | G62: ='Balance sheet'!F11+'Balance sheet'!F12+'Balance sheet'!F13+'Balance sheet'!F14+'Balance sheet'!F17+'Balance sheet'!F18 -> 947664 | J62: =B62 -> Other intangible assets | K62: =C62/$C$71 -> 0.06004977 | L62: =D62/$D$71 -> 0.047858878 | M62: =E62/$E$71 -> 0.054878859 | N62: =F62/$F$71 -> 0.1048321 | O62: =G62/$G$71 -> 0.079033053 | Q62: =L62-K62 -> -0.012190892 | R62: =(E62/D62)-1 -> 0.42105855 | S62: =(F62/E62)-1 -> 1.3123888 | T62: =(G62/F62)-1 -> -0.1689119 | U62: =(((G62/D62)^(1/3))-1) -> 0.39778369
B63: Goodwill | C63: ='Balance sheet'!B15 -> 2059 | D63: ='Balance sheet'!C15 -> 1625 | E63: ='Balance sheet'!D15 -> 1190 | F63: ='Balance sheet'!E15 -> 755 | G63: ='Balance sheet'!F15 -> 320 | J63: =B63 -> Goodwill | K63: =C63/$C$71 -> 0.00030138325 | L63: =D63/$D$71 -> 0.0002241204 | M63: =E63/$E$71 -> 0.00013243586 | N63: =F63/$F$71 -> 6.9411896e-05 | O63: =G63/$G$71 -> 2.6687283e-05 | Q63: =L63-K63 -> -7.7262842e-05 | R63: =(E63/D63)-1 -> -0.26769231 | S63: =(F63/E63)-1 -> -0.36554622 | T63: =(G63/F63)-1 -> -0.57615894 | U63: =(((G63/D63)^(1/3))-1) -> -0.41821096
B64: Other current assets | C64: ='Balance sheet'!B103+'Balance sheet'!B80+'Balance sheet'!B76+'Balance sheet'!B68 -> 2610934 | D64: ='Balance sheet'!C103+'Balance sheet'!C80+'Balance sheet'!C76+'Balance sheet'!C68 -> 3175648 | E64: ='Balance sheet'!D103+'Balance sheet'!D80+'Balance sheet'!D76+'Balance sheet'!D68 -> 4637423 | F64: ='Balance sheet'!E103+'Balance sheet'!E80+'Balance sheet'!E76+'Balance sheet'!E68 -> 4422528 | G64: ='Balance sheet'!F103+'Balance sheet'!F80+'Balance sheet'!F76+'Balance sheet'!F68 -> 6106805 | J64: Other current assets | K64: =C64/$C$71 -> 0.38217181 | L64: =D64/$D$71 -> 0.43798616 | M64: =E64/$E$71 -> 0.51610175 | N64: =F64/$F$71 -> 0.4065908 | O64: =G64/$G$71 -> 0.50929385 | Q64: =L64-K64 -> 0.055814348 | R64: =(E64/D64)-1 -> 0.46030763 | S64: =(F64/E64)-1 -> -0.046339314 | T64: =(G64/F64)-1 -> 0.38084032 | U64: =(((G64/D64)^(1/3))-1) -> 0.24354231
B65: Other non-current assets | C65: ='Balance sheet'!B77+'Balance sheet'!B79+'Balance sheet'!B81 -> 0 | D65: ='Balance sheet'!C77+'Balance sheet'!C79+'Balance sheet'!C81 -> 0 | E65: ='Balance sheet'!D77+'Balance sheet'!D79+'Balance sheet'!D81 -> 0 | F65: ='Balance sheet'!E77+'Balance sheet'!E79+'Balance sheet'!E81 -> 0 | G65: ='Balance sheet'!F77+'Balance sheet'!F79+'Balance sheet'!F81 -> 0 | J65: =B65 -> Other non-current assets | K65: =C65/$C$71 -> 0 | L65: =D65/$D$71 -> 0 | M65: =E65/$E$71 -> 0 | N65: =F65/$F$71 -> 0 | O65: =G65/$G$71 -> 0 | Q65: =L65-K65 -> 0 | R65: 0 | S65: 0 | T65: 0 | U65: 0
B66: Total Operating Assets | C66: =SUM(C59:C65) -> 6708600 | D66: =SUM(D59:D65) -> 6766164 | E66: =SUM(E59:E65) -> 8845278 | F66: =SUM(F59:F65) -> 10164691 | G66: =SUM(G59:G65) -> 11515958 | J66: Total Operating Assets | K66: =C66/$C$71 -> 0.98196194 | L66: =D66/$D$71 -> 0.93319102 | M66: =E66/$E$71 -> 0.98439661 | N66: =F66/$F$71 -> 0.93450395 | O66: =G66/$G$71 -> 0.96040508 | Q66: =L66-K66 -> -0.048770924 | R66: =(E66/D66)-1 -> 0.30728105 | S66: =(F66/E66)-1 -> 0.1491658 | T66: =(G66/F66)-1 -> 0.13293734 | U66: =(((G66/D66)^(1/3))-1) -> 0.19394921
B67: Cash and cash equivalents | C67: ='Balance sheet'!B98 -> 72963 | D67: ='Balance sheet'!C98 -> 434133 | E67: ='Balance sheet'!D98 -> 89934 | F67: ='Balance sheet'!E98 -> 662137 | G67: ='Balance sheet'!F98 -> 424502 | J67: =B67 -> Cash and cash equivalents | K67: =C67/$C$71 -> 0.010679857 | L67: =D67/$D$71 -> 0.059875731 | M67: =E67/$E$71 -> 0.010008812 | N67: =F67/$F$71 -> 0.060874417 | O67: =G67/$G$71 -> 0.035402515 | Q67: =L67-K67 -> 0.049195874 | R67: =(E67/D67)-1 -> -0.79284229 | S67: =(F67/E67)-1 -> 6.3624769 | T67: =(G67/F67)-1 -> -0.35889098 | U67: =(((G67/D67)^(1/3))-1) -> -0.0074501826
B68: Investment in associated companies | J68: =B68 -> Investment in associated companies | K68: =C68/$C$71 -> 0 | L68: =D68/$D$71 -> 0 | M68: =E68/$E$71 -> 0 | N68: =F68/$F$71 -> 0 | O68: =G68/$G$71 -> 0 | Q68: =L68-K68 -> 0 | R68: 0 | S68: 0 | T68: 0 | U68: 0
B69: Other financial assets | C69: ='Balance sheet'!B33+'Balance sheet'!B37 -> 50270 | D69: ='Balance sheet'!C33+'Balance sheet'!C37 -> 50270 | E69: ='Balance sheet'!D33+'Balance sheet'!D37 -> 50270 | F69: ='Balance sheet'!E33+'Balance sheet'!E37 -> 50270 | G69: ='Balance sheet'!F33+'Balance sheet'!F37 -> 50270 | J69: Other financial assets | K69: =C69/$C$71 -> 0.0073582009 | L69: =D69/$D$71 -> 0.0069332509 | M69: =E69/$E$71 -> 0.0055945802 | N69: =F69/$F$71 -> 0.0046216371 | O69: =G69/$G$71 -> 0.0041924053 | Q69: =L69-K69 -> -0.00042495006 | R69: =(E69/D69)-1 -> 0 | S69: =(F69/E69)-1 -> 0 | T69: =(G69/F69)-1 -> 0 | U69: =(((G69/D69)^(1/3))-1) -> 0
B70: Total Financial Assets | C70: =C67+C68+C69 -> 123233 | D70: =D67+D68+D69 -> 484403 | E70: =E67+E68+E69 -> 140204 | F70: =F67+F68+F69 -> 712407 | G70: =G67+G68+G69 -> 474772 | J70: Total Financial Assets | K70: =C70/$C$71 -> 0.018038058 | L70: =D70/$D$71 -> 0.066808982 | M70: =E70/$E$71 -> 0.015603392 | N70: =F70/$F$71 -> 0.065496054 | O70: =G70/$G$71 -> 0.03959492 | Q70: =L70-K70 -> 0.048770924 | R70: =(E70/D70)-1 -> -0.71056331 | S70: =(F70/E70)-1 -> 4.0812174 | T70: =(G70/F70)-1 -> -0.33356635 | U70: =(((G70/D70)^(1/3))-1) -> -0.006671816
B71: TOTAL ASSETS | C71: =C66+C70 -> 6831833 | D71: =D66+D70 -> 7250567 | E71: =E66+E70 -> 8985482 | F71: =F66+F70 -> 10877098 | G71: =G66+G70 -> 11990730 | J71: TOTAL ASSETS | K71: =C71/$C$71 -> 1 | L71: =D71/$D$71 -> 1 | M71: =E71/$E$71 -> 1 | N71: =F71/$F$71 -> 1 | O71: =G71/$G$71 -> 1 | R71: =(E71/D71)-1 -> 0.23927991 | S71: =(F71/E71)-1 -> 0.21051915 | T71: =(G71/F71)-1 -> 0.10238319 | U71: =(((G71/D71)^(1/3))-1) -> 0.18256372
B72: LIABILITIES AND EQUITY | J72: LIABILITIES AND EQUITY | Q72: =L72-K72 -> 0
B73: Operating Liabilities | J73: Operating Liabilities | Q73: =L73-K73 -> 0
B74: Trade Creditors | C74: ='Balance sheet'!B161+'Balance sheet'!B162 -> 1047973 | D74: ='Balance sheet'!C161+'Balance sheet'!C162 -> 1023644 | E74: ='Balance sheet'!D161+'Balance sheet'!D162 -> 1770389 | F74: ='Balance sheet'!E161+'Balance sheet'!E162 -> 1844400 | G74: ='Balance sheet'!F161+'Balance sheet'!F162 -> 1259596 | J74: Trade Creditors | K74: =C74/$G$71 -> 0.087398599 | L74: =D74/$G$71 -> 0.085369615 | M74: =E74/$G$71 -> 0.14764647 | N74: =F74/$G$71 -> 0.15381883 | O74: =G74/$G$71 -> 0.10504748 | Q74: =L74-K74 -> -0.0020289841 | R74: =(E74/D74)-1 -> 0.72949678 | S74: =(F74/E74)-1 -> 0.041804937 | T74: =(G74/F74)-1 -> -0.31707005 | U74: =(((G74/D74)^(1/3))-1) -> 0.071587015
B75: Other creditors | C75: ='Balance sheet'!B177+'Balance sheet'!B178 -> 439097 | D75: ='Balance sheet'!C177+'Balance sheet'!C178 -> 438760 | E75: ='Balance sheet'!D177+'Balance sheet'!D178 -> 541150 | F75: ='Balance sheet'!E177+'Balance sheet'!E178 -> 483612 | G75: ='Balance sheet'!F177+'Balance sheet'!F178 -> 536222 | J75: Other creditors | K75: =C75/$G$71 -> 0.036619705 | L75: =D75/$G$71 -> 0.0365916 | M75: =E75/$G$71 -> 0.045130697 | N75: =F75/$G$71 -> 0.040332157 | O75: =G75/$G$71 -> 0.044719713 | Q75: =L75-K75 -> -2.8105044e-05 | R75: =(E75/D75)-1 -> 0.2333622 | S75: =(F75/E75)-1 -> -0.10632542 | T75: =(G75/F75)-1 -> 0.10878556 | U75: =(((G75/D75)^(1/3))-1) -> 0.069151378
B76: Income tax payable | C76: ='Balance sheet'!B173+'Balance sheet'!B174 -> 25687 | D76: ='Balance sheet'!C173+'Balance sheet'!C174 -> 43393 | E76: ='Balance sheet'!D173+'Balance sheet'!D174 -> 155494 | F76: ='Balance sheet'!E173+'Balance sheet'!E174 -> 75574 | G76: ='Balance sheet'!F173+'Balance sheet'!F174 -> 105048 | J76: Income tax payable | K76: =C76/$G$71 -> 0.0021422382 | L76: =D76/$G$71 -> 0.0036188789 | M76: =E76/$G$71 -> 0.012967851 | N76: =F76/$G$71 -> 0.0063027022 | O76: =G76/$G$71 -> 0.0087607677 | Q76: =L76-K76 -> 0.0014766407 | R76: =(E76/D76)-1 -> 2.583389 | S76: =(F76/E76)-1 -> -0.51397482 | T76: =(G76/F76)-1 -> 0.39000185 | U76: =(((G76/D76)^(1/3))-1) -> 0.3427321
B77: Social expenditure payable | C77: ='Balance sheet'!B175++'Balance sheet'!B176 -> 40044 | D77: ='Balance sheet'!C175++'Balance sheet'!C176 -> 10997 | E77: ='Balance sheet'!D175++'Balance sheet'!D176 -> 30014 | F77: ='Balance sheet'!E175++'Balance sheet'!E176 -> 56938 | G77: ='Balance sheet'!F175++'Balance sheet'!F176 -> 63738 | J77: Social expenditure payable | K77: =C77/$G$71 -> 0.0033395798 | L77: =D77/$G$71 -> 0.00091712515 | M77: =E77/$G$71 -> 0.0025031003 | N77: =F77/$G$71 -> 0.0047485016 | O77: =G77/$G$71 -> 0.0053156063 | Q77: =L77-K77 -> -0.0024224547 | R77: =(E77/D77)-1 -> 1.7292898 | S77: =(F77/E77)-1 -> 0.89704804 | T77: =(G77/F77)-1 -> 0.11942815 | U77: =(((G77/D77)^(1/3))-1) -> 0.7962829
B78: Other current liabilities | C78: ='Balance sheet'!B165+'Balance sheet'!B185 -> 201200 | D78: ='Balance sheet'!C165+'Balance sheet'!C185 -> 247066 | E78: ='Balance sheet'!D165+'Balance sheet'!D185 -> 264645 | F78: ='Balance sheet'!E165+'Balance sheet'!E185 -> 474685 | G78: ='Balance sheet'!F165+'Balance sheet'!F185 -> 509596 | J78: Other current liabilities | K78: =C78/$G$71 -> 0.016779629 | L78: =D78/$G$71 -> 0.020604751 | M78: =E78/$G$71 -> 0.0220708 | N78: =F78/$G$71 -> 0.039587665 | O78: =G78/$G$71 -> 0.042499164 | Q78: =L78-K78 -> 0.0038251216 | R78: =(E78/D78)-1 -> 0.071151028 | S78: =(F78/E78)-1 -> 0.79366699 | T78: =(G78/F78)-1 -> 0.073545614 | U78: =(((G78/D78)^(1/3))-1) -> 0.27292947
B79: Total Operating Liabilities | C79: =SUM(C74:C78) -> 1754001 | D79: =SUM(D74:D78) -> 1763860 | E79: =SUM(E74:E78) -> 2761692 | F79: =SUM(F74:F78) -> 2935209 | G79: =SUM(G74:G78) -> 2474200 | J79: Total Operating Liabilities | K79: =C79/$C$71 -> 0.25673944 | L79: =D79/$D$71 -> 0.24327201 | M79: =E79/$E$71 -> 0.30735046 | N79: =F79/$F$71 -> 0.26985222 | O79: =G79/$G$71 -> 0.20634273 | Q79: =L79-K79 -> -0.013467434 | R79: =(E79/D79)-1 -> 0.5657093 | S79: =(F79/E79)-1 -> 0.062829961 | T79: =(G79/F79)-1 -> -0.15706173 | U79: =(((G79/D79)^(1/3))-1) -> 0.1194127
B80: Financial Liabilities | J80: Financial Liabilities | Q80: =L80-K80 -> 0
B81: Current portion of long-term debt | C81: ='Balance sheet'!B155 -> 954402 | D81: ='Balance sheet'!C155 -> 408353 | E81: ='Balance sheet'!D155 -> 1174483 | F81: ='Balance sheet'!E155 -> 893797 | G81: ='Balance sheet'!F155 -> 2067585 | J81: Current portion of long-term debt | K81: =C81/$C$71 -> 0.13969926 | L81: =D81/$D$71 -> 0.056320147 | M81: =E81/$E$71 -> 0.13070896 | N81: =F81/$F$71 -> 0.082172377 | O81: =G81/$G$71 -> 0.17243195 | Q81: =L81-K81 -> -0.083379111 | R81: =(E81/D81)-1 -> 1.8761464 | S81: =(F81/E81)-1 -> -0.23898686 | T81: =(G81/F81)-1 -> 1.3132602 | U81: =(((G81/D81)^(1/3))-1) -> 0.71715385
B82: Current loans & overdrafts | C82: 0 | D82: 0 | E82: 0 | F82: 0 | G82: 0 | J82: Current loans & overdrafts | K82: =C82/$C$71 -> 0 | L82: =D82/$D$71 -> 0 | M82: =E82/$E$71 -> 0 | N82: =F82/$F$71 -> 0 | O82: =G82/$G$71 -> 0 | Q82: =L82-K82 -> 0 | R82: 0 | S82: 0 | T82: 0 | U82: 0
B83: Other short-term debt | C83: 0 | D83: 0 | E83: 0 | F83: 0 | G83: 0 | J83: Other short-term debt | K83: =C83/$C$71 -> 0 | L83: =D83/$D$71 -> 0 | M83: =E83/$E$71 -> 0 | N83: =F83/$F$71 -> 0 | O83: =G83/$G$71 -> 0 | Q83: =L83-K83 -> 0 | R83: 0 | S83: 0 | T83: 0 | U83: 0
B84: Total long-term interest-bearing debt | C84: ='Balance sheet'!B156+'Balance sheet'!B158+'Balance sheet'!B154 -> 3267673 | D84: ='Balance sheet'!C156+'Balance sheet'!C158+'Balance sheet'!C154 -> 3890830 | E84: ='Balance sheet'!D156+'Balance sheet'!D158 -> 3314910 | F84: ='Balance sheet'!E156+'Balance sheet'!E158 -> 4483132 | G84: ='Balance sheet'!F156+'Balance sheet'!F158 -> 4243554 | J84: Total long-term interest-bearing debt | K84: =C84/$C$71 -> 0.47830107 | L84: =D84/$D$71 -> 0.53662424 | M84: =E84/$E$71 -> 0.36891844 | N84: =F84/$F$71 -> 0.41216251 | O84: =G84/$G$71 -> 0.35390289 | Q84: =L84-K84 -> 0.058323174 | R84: =(E84/D84)-1 -> -0.14801983 | S84: =(F84/E84)-1 -> 0.35241439 | T84: =(G84/F84)-1 -> -0.053439872 | U84: =(((G84/D84)^(1/3))-1) -> 0.029348634
B85: Total other non-current liabilities | C85: ='Balance sheet'!B144 -> 193620 | D85: ='Balance sheet'!C144 -> 220634 | E85: ='Balance sheet'!D144 -> 253701 | F85: ='Balance sheet'!E144 -> 307482 | G85: ='Balance sheet'!F144 -> 275626 | J85: Total other non-current liabilities | K85: =C85/$C$71 -> 0.028340857 | L85: =D85/$D$71 -> 0.030429896 | M85: =E85/$E$71 -> 0.028234545 | N85: =F85/$F$71 -> 0.028268753 | O85: =G85/$G$71 -> 0.02298659 | Q85: =L85-K85 -> 0.0020890393 | R85: =(E85/D85)-1 -> 0.14987264 | S85: =(F85/E85)-1 -> 0.21198576 | T85: =(G85/F85)-1 -> -0.10360281 | U85: =(((G85/D85)^(1/3))-1) -> 0.077000524
B86: Total Financial Liabilities | C86: =SUM(C81:C85) -> 4415695 | D86: =SUM(D81:D85) -> 4519817 | E86: =SUM(E81:E85) -> 4743094 | F86: =SUM(F81:F85) -> 5684411 | G86: =SUM(G81:G85) -> 6586765 | J86: Total Financial Liabilities | K86: =C86/$C$71 -> 0.64634118 | L86: =D86/$D$71 -> 0.62337428 | M86: =E86/$E$71 -> 0.52786194 | N86: =F86/$F$71 -> 0.52260364 | O86: =G86/$G$71 -> 0.54932143 | Q86: =L86-K86 -> -0.022966897 | R86: =(E86/D86)-1 -> 0.049399566 | S86: =(F86/E86)-1 -> 0.19846054 | T86: =(G86/F86)-1 -> 0.15874186 | U86: =(((G86/D86)^(1/3))-1) -> 0.13374949
B87: TOTAL LIABILITIES | C87: =C86+C79 -> 6169696 | D87: =D86+D79 -> 6283677 | E87: =E86+E79 -> 7504786 | F87: =F86+F79 -> 8619620 | G87: =G86+G79 -> 9060965 | J87: TOTAL LIABILITIES | K87: =C87/$C$71 -> 0.90308062 | L87: =D87/$D$71 -> 0.86664629 | M87: =E87/$E$71 -> 0.8352124 | N87: =F87/$F$71 -> 0.79245586 | O87: =G87/$G$71 -> 0.75566417 | Q87: =L87-K87 -> -0.036434331 | R87: =(E87/D87)-1 -> 0.19433033 | S87: =(F87/E87)-1 -> 0.14854974 | T87: =(G87/F87)-1 -> 0.051202373 | U87: =(((G87/D87)^(1/3))-1) -> 0.12976175
B88: Shareholders Equity | J88: Shareholders Equity | Q88: =L88-K88 -> 0
B89: Share Capital | C89: ='Balance sheet'!B113 -> 100000 | D89: ='Balance sheet'!C113 -> 100000 | E89: ='Balance sheet'!D113 -> 100000 | F89: ='Balance sheet'!E113 -> 100000 | G89: ='Balance sheet'!F113 -> 100000 | J89: Share Capital | K89: =C89/$C$71 -> 0.01463736 | L89: =D89/$D$71 -> 0.013792025 | M89: =E89/$E$71 -> 0.011129064 | N89: =F89/$F$71 -> 0.0091936287 | O89: =G89/$G$71 -> 0.0083397758 | Q89: =L89-K89 -> -0.00084533532 | R89: =(E89/D89)-1 -> 0 | S89: =(F89/E89)-1 -> 0 | T89: =(G89/F89)-1 -> 0 | U89: =(((G89/D89)^(1/3))-1) -> 0
B90: Other shareholders' funds | C90: ='Balance sheet'!B120+'Balance sheet'!B123+'Balance sheet'!B125 -> 542433 | D90: ='Balance sheet'!C120+'Balance sheet'!C123+'Balance sheet'!C125 -> 542436 | E90: ='Balance sheet'!D120+'Balance sheet'!D123+'Balance sheet'!D125 -> 542434 | F90: ='Balance sheet'!E120+'Balance sheet'!E123+'Balance sheet'!E125 -> 542436 | G90: ='Balance sheet'!F120+'Balance sheet'!F123+'Balance sheet'!F125 -> 542433 | J90: Other shareholders' funds | K90: =C90/$C$71 -> 0.079397872 | L90: =D90/$D$71 -> 0.074812908 | M90: =E90/$E$71 -> 0.060367824 | N90: =F90/$F$71 -> 0.049869552 | O90: =G90/$G$71 -> 0.045237696 | Q90: =L90-K90 -> -0.004584964 | R90: =(E90/D90)-1 -> -3.6870709e-06 | S90: =(F90/E90)-1 -> 3.6870845e-06 | T90: =(G90/F90)-1 -> -5.5306064e-06 | U90: =(((G90/D90)^(1/3))-1) -> -1.8435389e-06
B91: Retained Earnings | C91: ='Balance sheet'!B126+'Balance sheet'!B127 -> 19704 | D91: ='Balance sheet'!C126+'Balance sheet'!C127 -> 324454 | E91: ='Balance sheet'!D126+'Balance sheet'!D127 -> 838262 | F91: ='Balance sheet'!E126+'Balance sheet'!E127 -> 1615042 | G91: ='Balance sheet'!F126+'Balance sheet'!F127 -> 2287332 | J91: Retained Earnings | K91: =C91/$C$71 -> 0.0028841454 | L91: =D91/$D$71 -> 0.044748776 | M91: =E91/$E$71 -> 0.093290711 | N91: =F91/$F$71 -> 0.14848096 | O91: =G91/$G$71 -> 0.19075836 | Q91: =L91-K91 -> 0.041864631 | R91: =(E91/D91)-1 -> 1.5836082 | S91: =(F91/E91)-1 -> 0.92665539 | T91: =(G91/F91)-1 -> 0.41626781 | U91: =(((G91/D91)^(1/3))-1) -> 0.91745578
B92: TOTAL EQUITY | C92: =SUM(C89:C91) -> 662137 | D92: =SUM(D89:D91) -> 966890 | E92: =SUM(E89:E91) -> 1480696 | F92: =SUM(F89:F91) -> 2257478 | G92: =SUM(G89:G91) -> 2929765 | J92: TOTAL EQUITY | K92: =C92/C$71 -> 0.096919377 | L92: =D92/D$71 -> 0.13335371 | M92: =E92/E$71 -> 0.1647876 | N92: =F92/F$71 -> 0.20754414 | O92: =G92/G$71 -> 0.24433583 | Q92: =L92-K92 -> 0.036434331 | R92: =(E92/D92)-1 -> 0.53140068 | S92: =(F92/E92)-1 -> 0.524606 | T92: =(G92/F92)-1 -> 0.29780445 | U92: =(((G92/D92)^(1/3))-1) -> 0.44705567
B93: TOTAL LIABILITIES AND EQUITY | C93: =C92+C87 -> 6831833 | D93: =D92+D87 -> 7250567 | E93: =E92+E87 -> 8985482 | F93: =F92+F87 -> 10877098 | G93: =G92+G87 -> 11990730 | J93: TOTAL LIABILITIES AND EQUITY | K93: =C93/$C$71 -> 1 | L93: =D93/$D$71 -> 1 | M93: =E93/$E$71 -> 1 | N93: =F93/$F$71 -> 1 | O93: =G93/$G$71 -> 1 | R93: =(E93/D93)-1 -> 0.23927991 | S93: =(F93/E93)-1 -> 0.21051915 | T93: =(G93/F93)-1 -> 0.10238319 | U93: =(((G93/D93)^(1/3))-1) -> 0.18256372
B95: Luis Trenker S.r.l. | J95: Luis Trenker S.r.l.
B96: REFORMULATED BALANCE SHEET: Invested Capital - Source of Capital | J96: REFORMULATED BALANCE SHEET: Invested Capital - Source of Capital | R96: YEAR TO YEAR GROWTH RATES
C97: 2020 | D97: 2021 | E97: 2022 | F97: 2023 | G97: 2024 | K97: 2020 | L97: 2021 | M97: 2022 | N97: 2023 | O97: 2024 | Q97: 2021 | R97: 2022 | S97: 2023 | T97: 2024 | U97: CAGR 2021-2024
B98: (€ millions) | J98: (€ millions)
B99: Operating Assets | C99: =C66 -> 6708600 | D99: =D66 -> 6766164 | E99: =E66 -> 8845278 | F99: =F66 -> 10164691 | G99: =G66 -> 11515958 | J99: Operating Assets | K99: =C99/C71 -> 0.98196194 | L99: =D99/D71 -> 0.93319102 | M99: =E99/E71 -> 0.98439661 | N99: =F99/F71 -> 0.93450395 | O99: =G99/G71 -> 0.96040508 | Q99: =L99-K99 -> -0.048770924 | R99: =(E99/D99)-1 -> 0.30728105 | S99: =(F99/E99)-1 -> 0.1491658 | T99: =(G99/F99)-1 -> 0.13293734 | U99: =(((G99/D99)^(1/3))-1) -> 0.19394921
B100: Operating Liabilities | C100: =C79 -> 1754001 | D100: =D79 -> 1763860 | E100: =E79 -> 2761692 | F100: =F79 -> 2935209 | G100: =G79 -> 2474200 | J100: Operating Liabilities | K100: =K79 -> 0.25673944 | L100: =L79 -> 0.24327201 | M100: =M79 -> 0.30735046 | N100: =N79 -> 0.26985222 | O100: =O79 -> 0.20634273 | Q100: =L100-K100 -> -0.013467434 | R100: =(E100/D100)-1 -> 0.5657093 | S100: =(F100/E100)-1 -> 0.062829961 | T100: =(G100/F100)-1 -> -0.15706173 | U100: =(((G100/D100)^(1/3))-1) -> 0.1194127
B101: Net Operating Assets (NOA) | C101: =C99-C100 -> 4954599 | D101: =D99-D100 -> 5002304 | E101: =E99-E100 -> 6083586 | F101: =F99-F100 -> 7229482 | G101: =G99-G100 -> 9041758 | J101: Net Operating Assets (NOA) | K101: =K99-K100 -> 0.7252225 | L101: =L99-L100 -> 0.68991901 | M101: =M99-M100 -> 0.67704615 | N101: =N99-N100 -> 0.66465173 | O101: =O99-O100 -> 0.75406235 | Q101: =L101-K101 -> -0.03530349 | R101: =(E101/D101)-1 -> 0.21615679 | S101: =(F101/E101)-1 -> 0.18835864 | T101: =(G101/F101)-1 -> 0.25067854 | U101: =(((G101/D101)^(1/3))-1) -> 0.21813176
B102: Financial Liabilities | C102: =C86 -> 4415695 | D102: =D86 -> 4519817 | E102: =E86 -> 4743094 | F102: =F86 -> 5684411 | G102: =G86 -> 6586765 | J102: Financial Liabilities | K102: =K86 -> 0.64634118 | L102: =L86 -> 0.62337428 | M102: =M86 -> 0.52786194 | N102: =N86 -> 0.52260364 | O102: =O86 -> 0.54932143 | Q102: =L102-K102 -> -0.022966897 | R102: =(E102/D102)-1 -> 0.049399566 | S102: =(F102/E102)-1 -> 0.19846054 | T102: =(G102/F102)-1 -> 0.15874186 | U102: =(((G102/D102)^(1/3))-1) -> 0.13374949
B103: Financial Assets | C103: =C70 -> 123233 | D103: =D70 -> 484403 | E103: =E70 -> 140204 | F103: =F70 -> 712407 | G103: =G70 -> 474772 | J103: Financial Assets | K103: =K70 -> 0.018038058 | L103: =L70 -> 0.066808982 | M103: =M70 -> 0.015603392 | N103: =N70 -> 0.065496054 | O103: =O70 -> 0.03959492 | Q103: =L103-K103 -> 0.048770924 | R103: =(E103/D103)-1 -> -0.71056331 | S103: =(F103/E103)-1 -> 4.0812174 | T103: =(G103/F103)-1 -> -0.33356635 | U103: =(((G103/D103)^(1/3))-1) -> -0.006671816
B104: Net Financial Obligation (NFO) | C104: =C102-C103 -> 4292462 | D104: =D102-D103 -> 4035414 | E104: =E102-E103 -> 4602890 | F104: =F102-F103 -> 4972004 | G104: =G102-G103 -> 6111993 | J104: Net Financial Obligation (NFO) (Net Financial Assets-NFA) | K104: =K102-K103 -> 0.62830312 | L104: =L102-L103 -> 0.5565653 | M104: =M102-M103 -> 0.51225855 | N104: =N102-N103 -> 0.45710759 | O104: =O102-O103 -> 0.50972651 | Q104: =L104-K104 -> -0.071737821 | R104: =(E104/D104)-1 -> 0.14062399 | S104: =(F104/E104)-1 -> 0.080191793 | T104: =(G104/F104)-1 -> 0.22928159 | U104: =(((G104/D104)^(1/3))-1) -> 0.1484134
...

Sheet Reformulated Income statement
B1: Table 2.e
B3: Luis Trenker S.r.l.
B4: CONSOLIDATED PROFIT & LOSS
C5: 2020 | D5: 2021 | E5: 2022 | F5: 2023 | G5: 2024
B6: (€ millions)
B7: Revenue | C7: ='Income statement'!B5 -> 10560719 | D7: ='Income statement'!C5 -> 9241787 | E7: ='Income statement'!D5 -> 12660706 | F7: ='Income statement'!E5 -> 14473142 | G7: ='Income statement'!F5 -> 14950204
B8: Total revenues and Operating income | C8: =C7 -> 10560719 | D8: =D7 -> 9241787 | E8: =E7 -> 12660706 | F8: =F7 -> 14473142 | G8: =G7 -> 14950204
B9: Cost of Good Sold | C9: =-'Income statement'!B15 -> -5324267 | D9: =-'Income statement'!C15 -> -4922052 | E9: =-'Income statement'!D15 -> -6273959 | F9: =-'Income statement'!E15 -> -7792575 | G9: =-'Income statement'!F15 -> -6960697
B10: Other operating income (expense) | C10: =-('Income statement'!B16+'Income statement'!B17+'Income statement'!B18+'Income statement'!B34+'Income statement'!B31) -> -4534698 | D10: =-('Income statement'!C16+'Income statement'!C17+'Income statement'!C18+'Income statement'!C34+'Income statement'!C31) -> -3430217 | E10: =-('Income statement'!D16+'Income statement'!D17+'Income statement'!D18+'Income statement'!D34+'Income statement'!D31) -> -4913467 | F10: =-('Income statement'!E16+'Income statement'!E17+'Income statement'!E18+'Income statement'!E34+'Income statement'!E31) -> -5071866 | G10: =-('Income statement'!F16+'Income statement'!F17+'Income statement'!F18+'Income statement'!F34+'Income statement'!F31) -> -6476440
B11: Total depreciation, amortization & depletion | C11: =-'Income statement'!B25 -> -393099 | D11: =-'Income statement'!C25 -> -342652 | E11: =-'Income statement'!D25 -> -584234 | F11: =-'Income statement'!E25 -> -352969 | G11: =-'Income statement'!F25 -> -406658
B12: Total operating expense | C12: =SUM(C9:C11) -> -10252064 | D12: =SUM(D9:D11) -> -8694921 | E12: =SUM(E9:E11) -> -11771660 | F12: =SUM(F9:F11) -> -13217410 | G12: =SUM(G9:G11) -> -13843795
B13: Operating profit (loss) EBIT | C13: =C8+C12 -> 308655 | D13: =D8+D12 -> 546866 | E13: =E8+E12 -> 889046 | F13: =F8+F12 -> 1255732 | G13: =G8+G12 -> 1106409
B14: Finance Revenue | C14: ='Income statement'!B44 -> 584 | D14: ='Income statement'!C44 -> 291 | E14: ='Income statement'!D44 -> 258 | F14: ='Income statement'!E44 -> 333 | G14: ='Income statement'!F44 -> 74265
B15: Finance Expense | C15: =-'Income statement'!B54 -> -191809 | D15: =-'Income statement'!C54 -> -166922 | E15: =-'Income statement'!D54 -> -173690 | F15: =-'Income statement'!E54 -> -240050 | G15: =-'Income statement'!F54 -> -382279
B16: Other non-operating and financial income (expenses) | C16: ='Income statement'!B57 -> -119 | D16: ='Income statement'!C57 -> -62 | E16: ='Income statement'!D57 -> -33 | F16: ='Income statement'!E57 -> -14 | G16: ='Income statement'!F57 -> -46
B17: Financial profit (loss) | C17: =SUM(C14:C16) -> -191344 | D17: =SUM(D14:D16) -> -166693 | E17: =SUM(E14:E16) -> -173465 | F17: =SUM(F14:F16) -> -239731 | G17: =SUM(G14:G16) -> -308060
B18: Financial assets adjustments | C18: ='Income statement'!B59 -> -89095 | D18: 0 | E18: 0 | F18: 0 | G18: 0
B19: Profit (loss) before tax (PBT) | C19: =C13+C17+C18 -> 28216 | D19: =D13+D17 -> 380173 | E19: =E13+E17 -> 715581 | F19: =F13+F17 -> 1016001 | G19: =G13+G17 -> 798349
B20: Income taxes | C20: =-'Income statement'!B82 -> -8512 | D20: =-'Income statement'!C82 -> -75423 | E20: =-'Income statement'!D82 -> -201773 | F20: =-'Income statement'!E82 -> -239221 | G20: =-'Income statement'!F82 -> -126060
B21: NET PROFIT (PAT) | C21: =C19+C20 -> 19704 | D21: =D19+D20 -> 304750 | E21: =E19+E20 -> 513808 | F21: =F19+F20 -> 776780 | G21: =G19+G20 -> 672289
B26: Luis Trenker S.r.l. | J26: Luis Trenker S.r.l.
B27: INCOME STATEMENT - Pre Tax Allocation | J27: INCOME STATEMENT - Pre Tax Allocation | Q27: YEAR TO YEAR GROWTH RATES
C28: 2020 | D28: 2021 | E28: 2022 | F28: 2023 | G28: 2024 | K28: 2020 | L28: 2021 | M28: 2022 | N28: 2023 | O28: 2024 | Q28: 2022 | R28: 2023 | S28: 2024 | T28: CAGR 2021-2024
B29: (€ millions) | J29: (€ millions)
B30: Revenues | C30: =C7 -> 10560719 | D30: =D7 -> 9241787 | E30: =E7 -> 12660706 | F30: =F7 -> 14473142 | G30: =G7 -> 14950204 | J30: Revenues | K30: =C30/$C$30 -> 1 | L30: =D30/$D$30 -> 1 | M30: =E30/$E$30 -> 1 | N30: =F30/$F$30 -> 1 | O30: =G30/$G$30 -> 1 | Q30: =(E30/D30)-1 -> 0.36994133 | R30: =(F30/E30)-1 -> 0.14315442 | S30: =(G30/F30)-1 -> 0.032961882 | T30: =((G30/D30)^(1/3))-1 -> 0.17389807
B31: COGS | C31: =C9 -> -5324267 | D31: =D9 -> -4922052 | E31: =E9 -> -6273959 | F31: =F9 -> -7792575 | G31: =G9 -> -6960697 | J31: COGS | K31: =C31/$C$30 -> -0.50415762 | L31: =D31/$D$30 -> -0.53258661 | M31: =E31/$E$30 -> -0.49554575 | N31: =F31/$F$30 -> -0.53841626 | O31: =G31/$G$30 -> -0.46559211 | Q31: =(E31/D31)-1 -> 0.27466329 | R31: =(F31/E31)-1 -> 0.24205067 | S31: =(G31/F31)-1 -> -0.10675265 | T31: =((G31/D31)^(1/3))-1 -> 0.12245475
B32: Gross Profit | C32: =C30+C31 -> 5236452 | D32: =D30+D31 -> 4319735 | E32: =E30+E31 -> 6386747 | F32: =F30+F31 -> 6680567 | G32: =G30+G31 -> 7989507 | J32: Gross Profit | K32: =C32/$C$30 -> 0.49584238 | L32: =D32/$D$30 -> 0.46741339 | M32: =E32/$E$30 -> 0.50445425 | N32: =F32/$F$30 -> 0.46158374 | O32: =G32/$G$30 -> 0.53440789 | Q32: =(E32/D32)-1 -> 0.47850435 | R32: =(F32/E32)-1 -> 0.046004641 | S32: =(G32/F32)-1 -> 0.19593247 | T32: =((G32/D32)^(1/3))-1 -> 0.22749847
B33: Operating Expenses | C33: =C34 -> -393099 | D33: =D34 -> -342652 | E33: =E34 -> -584234 | F33: =F34 -> -352969 | G33: =G34 -> -406658 | J33: Operating Expenses | K33: =C33/$C$30 -> -0.03722275 | L33: =D33/$D$30 -> -0.037076379 | M33: =E33/$E$30 -> -0.046145452 | N33: =F33/$F$30 -> -0.024387863 | O33: =G33/$G$30 -> -0.027200833 | Q33: =(E33/D33)-1 -> 0.70503601 | R33: =(F33/E33)-1 -> -0.3958431 | S33: =(G33/F33)-1 -> 0.15210684 | T33: =((G33/D33)^(1/3))-1 -> 0.05874657
B34: =B11 -> Total depreciation, amortization & depletion | C34: =C11 -> -393099 | D34: =D11 -> -342652 | E34: =E11 -> -584234 | F34: =F11 -> -352969 | G34: =G11 -> -406658 | J34: =B34 -> Total depreciation, amortization & depletion | K34: =C34/$C$30 -> -0.03722275 | L34: =D34/$D$30 -> -0.037076379 | M34: =E34/$E$30 -> -0.046145452 | N34: =F34/$F$30 -> -0.024387863 | O34: =G34/$G$30 -> -0.027200833 | Q34: =(E34/D34)-1 -> 0.70503601 | R34: =(F34/E34)-1 -> -0.3958431 | S34: =(G34/F34)-1 -> 0.15210684 | T34: =((G34/D34)^(1/3))-1 -> 0.05874657
B35: Core operating Income | C35: =C32+C33 -> 4843353 | D35: =D32+D33 -> 3977083 | E35: =E32+E33 -> 5802513 | F35: =F32+F33 -> 6327598 | G35: =G32+G33 -> 7582849 | J35: Core operating Income | K35: =C35/$C$30 -> 0.45861963 | L35: =D35/$D$30 -> 0.43033701 | M35: =E35/$E$30 -> 0.4583088 | N35: =F35/$F$30 -> 0.43719588 | O35: =G35/$G$30 -> 0.50720706 | Q35: =(E35/D35)-1 -> 0.45898715 | R35: =(F35/E35)-1 -> 0.090492688 | S35: =(G35/F35)-1 -> 0.19837717 | T35: =((G35/D35)^(1/3))-1 -> 0.24000257
B36: Other operating income (expense) | C36: =C10 -> -4534698 | D36: =D10 -> -3430217 | E36: =E10 -> -4913467 | F36: =F10 -> -5071866 | G36: =G10 -> -6476440 | J36: Other operating income (expense) | K36: =C36/$C$30 -> -0.42939292 | L36: =D36/$D$30 -> -0.37116382 | M36: =E36/$E$30 -> -0.38808792 | N36: =F36/$F$30 -> -0.35043296 | O36: =G36/$G$30 -> -0.43320078 | Q36: =(E36/D36)-1 -> 0.43240705 | R36: =(F36/E36)-1 -> 0.032237725 | S36: =(G36/F36)-1 -> 0.27693437 | T36: =((G36/D36)^(1/3))-1 -> 0.23596143
B37: Operating Income | C37: =C35+C36 -> 308655 | D37: =D35+D36 -> 546866 | E37: =E35+E36 -> 889046 | F37: =F35+F36 -> 1255732 | G37: =G35+G36 -> 1106409 | J37: Operating Income | K37: =C37/$C$30 -> 0.029226703 | L37: =D37/$D$30 -> 0.059173188 | M37: =E37/$E$30 -> 0.070220887 | N37: =F37/$F$30 -> 0.086762916 | O37: =G37/$G$30 -> 0.074006281 | Q37: =(E37/D37)-1 -> 0.62571087 | R37: =(F37/E37)-1 -> 0.41244885 | S37: =(G37/F37)-1 -> -0.11891311 | T37: =((G37/D37)^(1/3))-1 -> 0.26477011
B38: Net Interest Income (expense) | C38: =SUM(C39:C42) -> -280439 | D38: =SUM(D39:D41) -> -166693 | E38: =SUM(E39:E41) -> -173465 | F38: =SUM(F39:F41) -> -239731 | G38: =SUM(G39:G41) -> -308060 | J38: Net Interest Income (expense) | K38: =C38/$C$30 -> -0.026554915 | L38: =D38/$D$30 -> -0.01803688 | M38: =E38/$E$30 -> -0.013701053 | N38: =F38/$F$30 -> -0.016563853 | O38: =G38/$G$30 -> -0.020605739 | Q38: =(E38/D38)-1 -> 0.040625581 | R38: =(F38/E38)-1 -> 0.38201366 | S38: =(G38/F38)-1 -> 0.28502363 | T38: =((G38/D38)^(1/3))-1 -> 0.22717354
B39: Financial Income | C39: =C14 -> 584 | D39: =D14 -> 291 | E39: =E14 -> 258 | F39: =F14 -> 333 | G39: =G14 -> 74265 | J39: Financial Income | K39: =C39/$C$30 -> 5.5299265e-05 | L39: =D39/$D$30 -> 3.1487417e-05 | M39: =E39/$E$30 -> 2.0378011e-05 | N39: =F39/$F$30 -> 2.3008135e-05 | O39: =G39/$G$30 -> 0.0049674907 | Q39: =(E39/D39)-1 -> -0.11340206 | R39: =(F39/E39)-1 -> 0.29069767 | S39: =(G39/F39)-1 -> 222.01802 | T39: =((G39/D39)^(1/3))-1 -> 5.3430344
B40: Financial Expense | C40: =C15 -> -191809 | D40: =D15 -> -166922 | E40: =E15 -> -173690 | F40: =F15 -> -240050 | G40: =G15 -> -382279 | J40: Financial Expense | K40: =C40/$C$30 -> -0.018162494 | L40: =D40/$D$30 -> -0.018061658 | M40: =E40/$E$30 -> -0.013718824 | N40: =F40/$F$30 -> -0.016585894 | O40: =G40/$G$30 -> -0.025570153 | Q40: =(E40/D40)-1 -> 0.040545884 | R40: =(F40/E40)-1 -> 0.38205999 | S40: =(G40/F40)-1 -> 0.5924974 | T40: =((G40/D40)^(1/3))-1 -> 0.31812204
B41: =B16 -> Other non-operating and financial income (expenses) | C41: =C16 -> -119 | D41: =D16 -> -62 | E41: =E16 -> -33 | F41: =F16 -> -14 | G41: =G16 -> -46 | J41: Other non operating and financial income(expense) | K41: =C41/$C$30 -> -1.1268172e-05 | L41: =D41/$D$30 -> -6.7086593e-06 | M41: =E41/$E$30 -> -2.6064897e-06 | N41: =F41/$F$30 -> -9.6730896e-07 | O41: =G41/$G$30 -> -3.0768811e-06 | Q41: =(E41/D41)-1 -> -0.46774194 | R41: =(F41/E41)-1 -> -0.57575758 | S41: =(G41/F41)-1 -> 2.2857143 | T41: =((G41/D41)^(1/3))-1 -> -0.094707934
B42: Financial asset adjustments | C42: ='Income statement'!B59 -> -89095 | D42: 0 | E42: 0 | F42: 0 | G42: 0 | J42: Financial asset adjustments | K42: =C42/$C$30 -> -0.0084364521 | L42: =D42/$D$30 -> 0 | M42: =E42/$E$30 -> 0 | N42: =F42/$F$30 -> 0 | O42: =G42/$F$30 -> 0 | Q42: 0 | R42: 0 | S42: 0 | T42: 0
B43: Earnings before Taxes (EBT) | C43: =C37+C38 -> 28216 | D43: =D37+D38 -> 380173 | E43: =E37+E38 -> 715581 | F43: =F37+F38 -> 1016001 | G43: =G37+G38 -> 798349 | J43: Earnings before Taxes (EBT) | K43: =C43/$C$30 -> 0.0026717878 | L43: =D43/$D$30 -> 0.041136308 | M43: =E43/$E$30 -> 0.056519834 | N43: =F43/$F$30 -> 0.070199063 | O43: =G43/$G$30 -> 0.053400542 | Q43: =(E43/D43)-1 -> 0.88225098 | R43: =(F43/E43)-1 -> 0.41982669 | S43: =(G43/F43)-1 -> -0.2142242 | T43: =((G43/D43)^(1/3))-1 -> 0.28057152
B44: Income Tax Expense | C44: =C20 -> -8512 | D44: =D20 -> -75423 | E44: =E20 -> -201773 | F44: =F20 -> -239221 | G44: =G20 -> -126060 | J44: Income Tax Expense | K44: =C44/$C$30 -> -0.00080600573 | L44: =D44/$D$30 -> -0.008161084 | M44: =E44/$E$30 -> -0.015936947 | N44: =F44/$F$30 -> -0.016528616 | O44: =G44/$G$30 -> -0.008431992 | Q44: =(E44/D44)-1 -> 1.6752184 | R44: =(F44/E44)-1 -> 0.1855947 | S44: =(G44/F44)-1 -> -0.47303957 | T44: =((G44/D44)^(1/3))-1 -> 0.18674616
B45: Net Income from continuing operations | C45: =C43+C44 -> 19704 | D45: =D43+D44 -> 304750 | E45: =E43+E44 -> 513808 | F45: =F43+F44 -> 776780 | G45: =G43+G44 -> 672289 | J45: Net Income from continuing operations | K45: =C45/$C$30 -> 0.0018657821 | L45: =D45/$D$30 -> 0.032975224 | M45: =E45/$E$30 -> 0.040582887 | N45: =F45/$F$30 -> 0.053670447 | O45: =G45/$G$30 -> 0.04496855 | Q45: =(E45/D45)-1 -> 0.68599836 | R45: =(F45/E45)-1 -> 0.51180986 | S45: =(G45/F45)-1 -> -0.13451814 | T45: =((G45/D45)^(1/3))-1 -> 0.30177951
B46: Income (loss) from discounted operations | C46: - | D46: - | E46: - | F46: - | G46: - | J46: Income (loss) from discounted operations | K46: - | L46: - | M46: - | N46: - | O46: - | Q46: - | R46: - | S46: - | T46: -
B47: Extraordinary gains (losses) | C47: - | D47: - | E47: - | F47: - | G47: - | J47: Extraordinary gains (losses) | K47: - | L47: - | M47: - | N47: - | O47: - | Q47: - | R47: - | S47: - | T47: -
B48: Changes in accounting principles | C48: - | D48: - | E48: - | F48: - | G48: - | J48: Changes in accounting principles | K48: - | L48: - | M48: - | N48: - | O48: - | Q48: - | R48: - | S48: - | T48: -
B49: Net Income | C49: =SUM(C45:C48) -> 19704 | D49: =SUM(D45:D48) -> 304750 | E49: =SUM(E45:E48) -> 513808 | F49: =SUM(F45:F48) -> 776780 | G49: =SUM(G45:G48) -> 672289 | J49: Net Income | K49: =C49/$C$30 -> 0.0018657821 | L49: =D49/$D$30 -> 0.032975224 | M49: =E49/$E$30 -> 0.040582887 | N49: =F49/$F$30 -> 0.053670447 | O49: =G49/$G$30 -> 0.04496855 | Q49: =M49-L49 -> 0.0076076625 | R49: =N49-M49 -> 0.01308756 | S49: =O49-N49 -> -0.0087018967 | T49: =((G49/D49)^(1/3))-1 -> 0.30177951
B52: Luis Trenker S.r.l.
B53: INCOME STATEMENT - After Tax Allocation | J53: INCOME STATEMENT - After Tax Allocation | Q53: YEAR TO YEAR GROWTH RATES
C54: 2020 | D54: 2021 | E54: 2022 | F54: 2023 | G54: 2024 | K54: 2020 | L54: 2021 | M54: 2022 | N54: 2023 | O54: 2024 | Q54: 2022 | R54: 2023 | S54: 2024 | T54: CAGR 2021-2024
B55: (€ millions) | J55: (€ millions)
B56: Revenues | C56: =C30 -> 10560719 | D56: =D30 -> 9241787 | E56: =E30 -> 12660706 | F56: =F30 -> 14473142 | G56: =G30 -> 14950204 | J56: Revenues | K56: =C56/$C$56 -> 1 | L56: =D56/$D$56 -> 1 | M56: =E56/$E$56 -> 1 | N56: =F56/$F$56 -> 1 | O56: =G56/$G$56 -> 1 | Q56: =(E56/D56)-1 -> 0.36994133 | R56: =(F56/E56)-1 -> 0.14315442 | S56: =(G56/F56)-1 -> 0.032961882 | T56: =((G56/D56)^(1/3))-1 -> 0.17389807
B57: COGS | C57: =C31 -> -5324267 | D57: =D31 -> -4922052 | E57: =E31 -> -6273959 | F57: =F31 -> -7792575 | G57: =G31 -> -6960697 | J57: COGS | K57: =C57/C$56 -> -0.50415762 | L57: =D57/D$56 -> -0.53258661 | M57: =E57/E$56 -> -0.49554575 | N57: =F57/F$56 -> -0.53841626 | O57: =G57/G$56 -> -0.46559211 | Q57: =(E57/D57)-1 -> 0.27466329 | R57: =(F57/E57)-1 -> 0.24205067 | S57: =(G57/F57)-1 -> -0.10675265 | T57: =((G57/D57)^(1/3))-1 -> 0.12245475
B58: Gross Profit | C58: =C32 -> 5236452 | D58: =D32 -> 4319735 | E58: =E32 -> 6386747 | F58: =F32 -> 6680567 | G58: =G32 -> 7989507 | J58: Gross Profit | K58: =C58/C$56 -> 0.49584238 | L58: =D58/D$56 -> 0.46741339 | M58: =E58/E$56 -> 0.50445425 | N58: =F58/F$56 -> 0.46158374 | O58: =G58/G$56 -> 0.53440789 | Q58: =(E58/D58)-1 -> 0.47850435 | R58: =(F58/E58)-1 -> 0.046004641 | S58: =(G58/F58)-1 -> 0.19593247 | T58: =((G58/D58)^(1/3))-1 -> 0.22749847
B59: Operating Expenses | C59: =C33 -> -393099 | D59: =D33 -> -342652 | E59: =E33 -> -584234 | F59: =F33 -> -352969 | G59: =G33 -> -406658 | J59: Operating Expenses | K59: =C59/C$56 -> -0.03722275 | L59: =D59/D$56 -> -0.037076379 | M59: =E59/E$56 -> -0.046145452 | N59: =F59/F$56 -> -0.024387863 | O59: =G59/G$56 -> -0.027200833 | Q59: =(E59/D59)-1 -> 0.70503601 | R59: =(F59/E59)-1 -> -0.3958431 | S59: =(G59/F59)-1 -> 0.15210684 | T59: =((G59/D59)^(1/3))-1 -> 0.05874657
B60: =B39 -> Financial Income | C60: =C34 -> -393099 | D60: =D34 -> -342652 | E60: =E34 -> -584234 | F60: =F34 -> -352969 | G60: =G34 -> -406658 | J60: =J39 -> Financial Income | K60: =C60/C$56 -> -0.03722275 | L60: =D60/D$56 -> -0.037076379 | M60: =E60/E$56 -> -0.046145452 | N60: =F60/F$56 -> -0.024387863 | O60: =G60/G$56 -> -0.027200833 | Q60: =(E60/D60)-1 -> 0.70503601 | R60: =(F60/E60)-1 -> -0.3958431 | S60: =(G60/F60)-1 -> 0.15210684 | T60: =((G60/D60)^(1/3))-1 -> 0.05874657
B61: Core operating Income | C61: =C35 -> 4843353 | D61: =D35 -> 3977083 | E61: =E35 -> 5802513 | F61: =F35 -> 6327598 | G61: =G35 -> 7582849 | J61: Core operating Income | K61: =C61/C$56 -> 0.45861963 | L61: =D61/D$56 -> 0.43033701 | M61: =E61/E$56 -> 0.4583088 | N61: =F61/F$56 -> 0.43719588 | O61: =G61/G$56 -> 0.50720706 | Q61: =(E61/D61)-1 -> 0.45898715 | R61: =(F61/E61)-1 -> 0.090492688 | S61: =(G61/F61)-1 -> 0.19837717 | T61: =((G61/D61)^(1/3))-1 -> 0.24000257
B62: Tax as reported | C62: =C44 -> -8512 | D62: =D44 -> -75423 | E62: =E44 -> -201773 | F62: =F44 -> -239221 | G62: =G44 -> -126060 | J62: Tax as reported | K62: =C62/C$56 -> -0.00080600573 | L62: =D62/D$56 -> -0.008161084 | M62: =E62/E$56 -> -0.015936947 | N62: =F62/F$56 -> -0.016528616 | O62: =G62/G$56 -> -0.008431992 | Q62: =(E62/D62)-1 -> 1.6752184 | R62: =(F62/E62)-1 -> 0.1855947 | S62: =(G62/F62)-1 -> -0.47303957 | T62: =((G62/D62)^(1/3))-1 -> 0.18674616
B63: Tax on (benefit from) other operating income | C63: =C36*D102 -> 0 | D63: =D36*E102 -> -680525.07 | E63: =E36*E103 -> -1385454.6 | F63: =F36*E104 -> -1194188.6 | G63: =G36*E105 -> -1022635.5 | J63: Tax on (benefit from) other operating income | K63: =C63/C$56 -> 0 | L63: =D63/D$56 -> -0.073635658 | M63: =E63/E$56 -> -0.10942949 | N63: =F63/F$56 -> -0.08251067 | O63: =G63/G$56 -> -0.068402779 | Q63: =(E63/D63)-1 -> 1.0358612 | R63: =(F63/E63)-1 -> -0.13805284 | S63: =(G63/F63)-1 -> -0.14365666 | T63: =((G63/D63)^(1/3))-1 -> 0.14540457
B64: Tax on (benefit from) net interest expenses | C64: =C38*D102 -> 0 | D64: =D38*E102 -> -33070.434 | E64: =E38*E103 -> -48912.078 | F64: =F38*E104 -> -56445.505 | G64: =G38*E105 -> -48642.941 | J64: Tax on (benefit from) net interest expenses | K64: =C64/C$56 -> 0 | L64: =D64/D$56 -> -0.0035783593 | M64: =E64/E$56 -> -0.0038632978 | N64: =F64/F$56 -> -0.0039000174 | O64: =G64/G$56 -> -0.0032536641 | Q64: =(E64/D64)-1 -> 0.47902739 | R64: =(F64/E64)-1 -> 0.15401978 | S64: =(G64/F64)-1 -> -0.1382318 | T64: =((G64/D64)^(1/3))-1 -> 0.13726056
B65: Total Tax on Core Operating Income | C65: =SUM(C62:C64) -> -8512 | D65: =SUM(D62:D64) -> -789018.5 | E65: =SUM(E62:E64) -> -1636139.7 | F65: =SUM(F62:F64) -> -1489855.1 | G65: =SUM(G62:G64) -> -1197338.4 | J65: Total Tax on Core Operating Income | K65: =C65/C$56 -> -0.00080600573 | L65: =D65/D$56 -> -0.085375101 | M65: =E65/E$56 -> -0.12922973 | N65: =F65/F$56 -> -0.1029393 | O65: =G65/G$56 -> -0.080088435 | Q65: =(E65/D65)-1 -> 1.0736392 | R65: =(F65/E65)-1 -> -0.089408329 | S65: =(G65/F65)-1 -> -0.19633903 | T65: =((G65/D65)^(1/3))-1 -> 0.14914962
B66: NOPAT Core | C66: =C61+C65 -> 4834841 | D66: =D61+D65 -> 3188064.5 | E66: =E61+E65 -> 4166373.3 | F66: =F61+F65 -> 4837742.9 | G66: =G61+G65 -> 6385510.6 | J66: NOPAT Core | K66: =C66/C$56 -> 0.45781362 | L66: =D66/D$56 -> 0.34496191 | M66: =E66/E$56 -> 0.32907907 | N66: =F66/F$56 -> 0.33425657 | O66: =G66/G$56 -> 0.42711862 | Q66: =(E66/D66)-1 -> 0.30686608 | R66: =(F66/E66)-1 -> 0.16114003 | S66: =(G66/F66)-1 -> 0.31993592 | T66: =((G66/D66)^(1/3))-1 -> 0.26053868
B67: Other operating income (expense) (before tax) | C67: =C36 -> -4534698 | D67: =D36 -> -3430217 | E67: =E36 -> -4913467 | F67: =F36 -> -5071866 | G67: =G36 -> -6476440 | J67: Other operating income (expense) (before tax) | K67: =C67/C$56 -> -0.42939292 | L67: =D67/D$56 -> -0.37116382 | M67: =E67/E$56 -> -0.38808792 | N67: =F67/F$56 -> -0.35043296 | O67: =G67/G$56 -> -0.43320078 | Q67: =(E67/D67)-1 -> 0.43240705 | R67: =(F67/E67)-1 -> 0.032237725 | S67: =(G67/F67)-1 -> 0.27693437 | T67: =((G67/D67)^(1/3))-1 -> 0.23596143
B68: Tax on other operating income | C68: =ABS(C63) -> 0 | D68: =ABS(D63) -> 680525.07 | E68: =ABS(E63) -> 1385454.6 | F68: =ABS(F63) -> 1194188.6 | G68: =ABS(G63) -> 1022635.5 | J68: Tax on other operating income | K68: =C68/C$56 -> 0 | L68: =D68/D$56 -> 0.073635658 | M68: =E68/E$56 -> 0.10942949 | N68: =F68/F$56 -> 0.08251067 | O68: =G68/G$56 -> 0.068402779 | Q68: =(E68/D68)-1 -> 1.0358612 | R68: =(F68/E68)-1 -> -0.13805284 | S68: =(G68/F68)-1 -> -0.14365666 | T68: =((G68/D68)^(1/3))-1 -> 0.14540457
B69: NOPAT | C69: =SUM(C66:C68) -> 300143 | D69: =SUM(D66:D68) -> 438372.57 | E69: =SUM(E66:E68) -> 638360.92 | F69: =SUM(F66:F68) -> 960065.49 | G69: =SUM(G66:G68) -> 931706.06 | J69: NOPAT | K69: =C69/C$56 -> 0.028420697 | L69: =D69/D$56 -> 0.047433745 | M69: =E69/E$56 -> 0.050420642 | N69: =F69/F$56 -> 0.066334283 | O69: =G69/G$56 -> 0.062320625 | Q69: =(E69/D69)-1 -> 0.45620637 | R69: =(F69/E69)-1 -> 0.50395405 | S69: =(G69/F69)-1 -> -0.029539064 | T69: =((G69/D69)^(1/3))-1 -> 0.2857164
B70: Net Interest Income (Expense) before tax | C70: =C38 -> -280439 | D70: =D38 -> -166693 | E70: =E38 -> -173465 | F70: =F38 -> -239731 | G70: =G38 -> -308060 | J70: Net Interest Income (Expense) before tax | K70: =C70/C$56 -> -0.026554915 | L70: =D70/D$56 -> -0.01803688 | M70: =E70/E$56 -> -0.013701053 | N70: =F70/F$56 -> -0.016563853 | O70: =G70/G$56 -> -0.020605739 | Q70: =(E70/D70)-1 -> 0.040625581 | R70: =(F70/E70)-1 -> 0.38201366 | S70: =(G70/F70)-1 -> 0.28502363 | T70: =((G70/D70)^(1/3))-1 -> 0.22717354
B71: Financial Income | C71: =C39 -> 584 | D71: =D39 -> 291 | E71: =E39 -> 258 | F71: =F39 -> 333 | G71: =G39 -> 74265 | J71: Financial Income | K71: =C71/C$56 -> 5.5299265e-05 | L71: =D71/D$56 -> 3.1487417e-05 | M71: =E71/E$56 -> 2.0378011e-05 | N71: =F71/F$56 -> 2.3008135e-05 | O71: =G71/G$56 -> 0.0049674907 | Q71: =(E71/D71)-1 -> -0.11340206 | R71: =(F71/E71)-1 -> 0.29069767 | S71: =(G71/F71)-1 -> 222.01802 | T71: =((G71/D71)^(1/3))-1 -> 5.3430344
B72: Financial Expense | C72: =C40 -> -191809 | D72: =D40 -> -166922 | E72: =E40 -> -173690 | F72: =F40 -> -240050 | G72: =G40 -> -382279 | J72: Financial Expense | K72: =C72/C$56 -> -0.018162494 | L72: =D72/D$56 -> -0.018061658 | M72: =E72/E$56 -> -0.013718824 | N72: =F72/F$56 -> -0.016585894 | O72: =G72/G$56 -> -0.025570153 | Q72: =(E72/D72)-1 -> 0.040545884 | R72: =(F72/E72)-1 -> 0.38205999 | S72: =(G72/F72)-1 -> 0.5924974 | T72: =((G72/D72)^(1/3))-1 -> 0.31812204
B73: =B41 -> Other non-operating and financial income (expenses) | C73: =C41 -> -119 | D73: =D41 -> -62 | E73: =E41 -> -33 | F73: =F41 -> -14 | G73: =G41 -> -46 | J73: Other non operating and financial income | K73: =C73/C$56 -> -1.1268172e-05 | L73: =D73/D$56 -> -6.7086593e-06 | M73: =E73/E$56 -> -2.6064897e-06 | N73: =F73/F$56 -> -9.6730896e-07 | O73: =G73/G$56 -> -3.0768811e-06 | Q73: =(E73/D73)-1 -> -0.46774194 | R73: =(F73/E73)-1 -> -0.57575758 | S73: =(G73/F73)-1 -> 2.2857143 | T73: =((G73/D73)^(1/3))-1 -> -0.094707934
B74: Financial asset adjustments | C74: ='Income statement'!B59 -> -89095 | D74: 0 | E74: 0 | F74: 0 | G74: 0 | J74: Financial asset adjustments | K74: =C74/C$56 -> -0.0084364521 | L74: =D74/D$56 -> 0 | M74: =E74/E$56 -> 0 | N74: =F74/F$56 -> 0 | O74: =G74/G$56 -> 0 | Q74: 0 | R74: 0 | S74: 0 | T74: 0
B75: Tax on (benefit from) net interest expenses | C75: =ABS(C64) -> 0 | D75: =ABS(D64) -> 33070.434 | E75: =ABS(E64) -> 48912.078 | F75: =ABS(F64) -> 56445.505 | G75: =ABS(G64) -> 48642.941 | J75: Tax on (benefit from) net interest expenses | K75: =C75/C$56 -> 0 | L75: =D75/D$56 -> 0.0035783593 | M75: =E75/E$56 -> 0.0038632978 | N75: =F75/F$56 -> 0.0039000174 | O75: =G75/G$56 -> 0.0032536641 | Q75: =(E75/D75)-1 -> 0.47902739 | R75: =(F75/E75)-1 -> 0.15401978 | S75: =(G75/F75)-1 -> -0.1382318 | T75: =((G75/D75)^(1/3))-1 -> 0.13726056
B76: Net financial Income (expenses) after tax | C76: =C70+C75 -> -280439 | D76: =D70+D75 -> -133622.57 | E76: =E70+E75 -> -124552.92 | F76: =F70+F75 -> -183285.49 | G76: =G70+G75 -> -259417.06 | J76: Net financial Income (expenses) after tax | K76: =C76/C$56 -> -0.026554915 | L76: =D76/D$56 -> -0.01445852 | M76: =E76/E$56 -> -0.0098377549 | N76: =F76/F$56 -> -0.012663836 | O76: =G76/G$56 -> -0.017352075 | Q76: =(E76/D76)-1 -> -0.067875089 | R76: =(F76/E76)-1 -> 0.47154713 | S76: =(G76/F76)-1 -> 0.41537146 | T76: =((G76/D76)^(1/3))-1 -> 0.24749719
B77: Net Income from continuing operations | C77: =C69+C76 -> 19704 | D77: =D69+D76 -> 304750 | E77: =E69+E76 -> 513808 | F77: =F69+F76 -> 776780 | G77: =G69+G76 -> 672289 | J77: Net Income from continuing operations | K77: =C77/C$56 -> 0.0018657821 | L77: =D77/D$56 -> 0.032975224 | M77: =E77/E$56 -> 0.040582887 | N77: =F77/F$56 -> 0.053670447 | O77: =G77/G$56 -> 0.04496855 | Q77: =(E77/D77)-1 -> 0.68599836 | R77: =(F77/E77)-1 -> 0.51180986 | S77: =(G77/F77)-1 -> -0.13451814 | T77: =((G77/D77)^(1/3))-1 -> 0.30177951
B78: Income (loss) from discounted operations | C78: - | D78: - | E78: - | F78: - | G78: - | J78: Income (loss) from discounted operations | K78: - | L78: - | M78: - | N78: - | O78: - | Q78: - | R78: - | S78: - | T78: -
B79: Extraordinary gains (losses) | C79: - | D79: - | E79: - | F79: - | G79: - | J79: Extraordinary gains (losses) | K79: - | L79: - | M79: - | N79: - | O79: - | Q79: - | R79: - | S79: - | T79: -
B80: Changes in accounting principles | C80: - | D80: - | E80: - | F80: - | G80: - | J80: Changes in accounting principles | K80: - | L80: - | M80: - | N80: - | O80: - | Q80: - | R80: - | S80: - | T80: -
B81: Net Income | C81: =SUM(C77:C80) -> 19704 | D81: =SUM(D77:D80) -> 304750 | E81: =SUM(E77:E80) -> 513808 | F81: =SUM(F77:F80) -> 776780 | G81: =SUM(G77:G80) -> 672289 | J81: Net Income | K81: =C81/C$56 -> 0.0018657821 | L81: =D81/D$56 -> 0.032975224 | M81: =E81/E$56 -> 0.040582887 | N81: =F81/F$56 -> 0.053670447 | O81: =G81/G$56 -> 0.04496855 | Q81: =(E81/D81)-1 -> 0.68599836 | R81: =(F81/E81)-1 -> 0.51180986 | S81: =(G81/F81)-1 -> -0.13451814 | T81: =((G81/D81)^(1/3))-1 -> 0.30177951
J83: Luis Trenker S.r.l.
B84: REFORMULATED INCOME STATEMENT - SIMPLIFIED | J84: REFORMULATED INCOME STATEMENT - SIMPLIFIED | Q84: YEAR TO YEAR GROWTH RATES
C85: 2020 | D85: 2021 | E85: 2022 | F85: 2023 | G85: 2024 | K85: 2020 | L85: 2021 | M85: 2022 | N85: 2023 | O85: 2024 | Q85: 2022 | R85: 2023 | S85: 2024 | T85: CAGR 2021-2024
B86: (€ millions) | J86: (€ millions)
B87: Revenues | C87: =C56 -> 10560719 | D87: =D56 -> 9241787 | E87: =E56 -> 12660706 | F87: =F56 -> 14473142 | G87: =G56 -> 14950204 | J87: Revenues | K87: =C87/$C$87 -> 1 | L87: =D87/$D$87 -> 1 | M87: =E87/$E$87 -> 1 | N87: =F87/$F$87 -> 1 | O87: =G87/$G$87 -> 1 | Q87: =((F87/E87)-1) -> 0.14315442 | R87: =((F87/E87)-1) -> 0.14315442 | S87: =((G87/F87)-1) -> 0.032961882 | T87: =((G87/D87)^(1/3)-1) -> 0.17389807
B88: Operating Expenses | C88: =C59 -> -393099 | D88: =D59 -> -342652 | E88: =E59 -> -584234 | F88: =F59 -> -352969 | G88: =G59 -> -406658 | J88: Operating Expenses | K88: =C88/$C$87 -> -0.03722275 | L88: =D88/$D$87 -> -0.037076379 | M88: =E88/$F$87 -> -0.04036677 | N88: =F88/$F$87 -> -0.024387863 | O88: =G88/$G$87 -> -0.027200833 | Q88: =((F88/E88)-1) -> -0.3958431 | R88: =((F88/E88)-1) -> -0.3958431 | S88: =((G88/F88)-1) -> 0.15210684 | T88: =((G88/D88)^(1/3)-1) -> 0.05874657
B89: Income Tax on core operating income items | C89: =C65 -> -8512 | D89: =D65 -> -789018.5 | E89: =E65 -> -1636139.7 | F89: =F65 -> -1489855.1 | G89: =G65 -> -1197338.4 | J89: Income Tax on core operating income items | K89: =C89/$C$87 -> -0.00080600573 | L89: =D89/$D$87 -> -0.085375101 | M89: =E89/$E$87 -> -0.12922973 | N89: =F89/$F$87 -> -0.1029393 | O89: =G89/$G$87 -> -0.080088435 | Q89: =((F89/E89)-1) -> -0.089408329 | R89: =((F89/E89)-1) -> -0.089408329 | S89: =((G89/F89)-1) -> -0.19633903 | T89: =((G89/D89)^(1/3)-1) -> 0.14914962
B90: Core Operating Income After Tax | C90: =C66 -> 4834841 | D90: =D66 -> 3188064.5 | E90: =E66 -> 4166373.3 | F90: =F66 -> 4837742.9 | G90: =G66 -> 6385510.6 | J90: Core Operating Income After Tax | K90: =C90/$C$87 -> 0.45781362 | L90: =D90/$D$87 -> 0.34496191 | M90: =E90/$E$87 -> 0.32907907 | N90: =F90/$F$87 -> 0.33425657 | O90: =G90/$G$87 -> 0.42711862 | Q90: =((F90/E90)-1) -> 0.16114003 | R90: =((G90/F90)-1) -> 0.31993592 | S90: =((G90/F90)-1) -> 0.31993592 | T90: =((G90/D90)^(1/3)-1) -> 0.26053868
B91: Operating Income (After tax effect) - NOPAT | C91: =C69 -> 300143 | D91: =D69 -> 438372.57 | E91: =E69 -> 638360.92 | F91: =F69 -> 960065.49 | G91: =G69 -> 931706.06 | J91: Operating Income (After tax effect) - NOPAT | K91: =C91/$C$87 -> 0.028420697 | L91: =D91/$D$87 -> 0.047433745 | M91: =E91/$E$87 -> 0.050420642 | N91: =F91/$F$87 -> 0.066334283 | O91: =G91/$G$87 -> 0.062320625 | Q91: =((F91/E91)-1) -> 0.50395405 | R91: =((G91/F91)-1) -> -0.029539064 | S91: =((G91/F91)-1) -> -0.029539064 | T91: =((G91/D91)^(1/3)-1) -> 0.2857164
B92: Net Financial Income (Expense) After Tax | C92: =C76 -> -280439 | D92: =D76 -> -133622.57 | E92: =E76 -> -124552.92 | F92: =F76 -> -183285.49 | G92: =G76 -> -259417.06 | J92: Net Financial Income (Expense) After Tax | K92: =C92/$C$87 -> -0.026554915 | L92: =D92/$D$87 -> -0.01445852 | M92: =E92/$E$87 -> -0.0098377549 | N92: =F92/$F$87 -> -0.012663836 | O92: =G92/$G$87 -> -0.017352075 | Q92: =((F92/E92)-1) -> 0.47154713 | R92: =((G92/F92)-1) -> 0.41537146 | S92: =((G92/F92)-1) -> 0.41537146 | T92: =((G92/D92)^(1/3)-1) -> 0.24749719
B93: Net Income from continuing operations | C93: =C77 -> 19704 | D93: =D77 -> 304750 | E93: =E77 -> 513808 | F93: =F77 -> 776780 | G93: =G77 -> 672289 | J93: Net Income from continuing operations | K93: =C93/$C$87 -> 0.0018657821 | L93: =D93/$D$87 -> 0.032975224 | M93: =E93/$E$87 -> 0.040582887 | N93: =F93/$F$87 -> 0.053670447 | O93: =G93/$G$87 -> 0.04496855 | Q93: =((F93/E93)-1) -> 0.51180986 | R93: =((G93/F93)-1) -> -0.13451814 | S93: =((G93/F93)-1) -> -0.13451814 | T93: =((G93/D93)^(1/3)-1) -> 0.30177951
B94: Extraordinary, discounted and change accounting principles | C94: - | D94: - | E94: - | F94: - | G94: - | J94: Extraordinary, discounted and change accounting principles | K94: - | L94: - | M94: - | N94: - | O94: - | Q94: - | R94: - | S94: - | T94: -
B95: Net Income | C95: =C81 -> 19704 | D95: =D81 -> 304750 | E95: =E81 -> 513808 | F95: =F81 -> 776780 | G95: =G81 -> 672289 | J95: Net Income | K95: =C95/$C$87 -> 0.0018657821 | L95: =D95/$D$87 -> 0.032975224 | M95: =E95/$E$87 -> 0.040582887 | N95: =F95/$F$87 -> 0.053670447 | O95: =G95/$G$87 -> 0.04496855 | Q95: =((F95/E95)-1) -> 0.51180986 | R95: =((G95/F95)-1) -> -0.13451814 | S95: =((G95/F95)-1) -> -0.13451814 | T95: =((G95/D95)^(1/3)-1) -> 0.30177951
B100: STATUTORY TAX RATE CALCULATION
B101: Year | E101: Tax = Tax /EBT | F101: Income tax expense | G101: EBT
B102: 2024 | E102: =ABS(F102)/G102 -> 0.19839126 | F102: =D44 -> -75423 | G102: =D43 -> 380173
B103: 2023 | E103: =ABS(F103)/G103 -> 0.28197087 | F103: =E44 -> -201773 | G103: =E43 -> 715581
B104: 2022 | E104: =ABS(F104)/G104 -> 0.23545351 | F104: =F44 -> -239221 | G104: =F43 -> 1016001
B105: 2021 | E105: =ABS(F105)/G105 -> 0.15790087 | F105: =G44 -> -126060 | G105: =G43 -> 798349

Sheet Cash flow
P1: Table 3.e
P3: Luis Trenker S.r.l.
B4: CONSOLIDATED PROFIT & LOSS | I4: CONSOLIDATED BALANCE SHEET | P4: REFORMULATED CASH FLOW
C5: 2020 | D5: 2021 | E5: 2022 | F5: 2023 | G5: 2024 | J5: 2020 | K5: 2021 | L5: 2022 | M5: 2023 | N5: 2024 | Q5: 2021 | R5: 20222 | S5: 2023 | T5: 2024
B6: (€ millions) | I6: (in Euro million) | P6: (€ millions)
B7: Revenue | C7: 10560719 | D7: 9241787 | E7: 12660706 | F7: 14473142 | G7: 14950204 | I7: ASSETS | P7: Net income | Q7: =D21 -> 304750 | R7: =E21 -> 513808 | S7: =F21 -> 776780 | T7: =G21 -> 672289
B8: Total revenues and Operating income | C8: 10560719 | D8: 9241787 | E8: 12660706 | F8: 14473142 | G8: 14950204 | I8: Non-current assets | P8: Depreciation and amortization | Q8: =-D11 -> 342652 | R8: =-E11 -> 584234 | S8: =-F11 -> 352969 | T8: =-G11 -> 406658
B9: Cost of Good Sold | C9: -5324267 | D9: -4922052 | E9: -6273959 | F9: -7792575 | G9: -6960697 | I9: Concessions | J9: 22091 | K9: 24644 | L9: 23054 | M9: 30220 | N9: 31737 | O9: x | P9: Changes in working capital
B10: Other operating income (expense) | C10: -4534698 | D10: -3430217 | E10: -4913467 | F10: -5071866 | G10: -6476440 | I10: Goodwill | J10: 2059 | K10: 1625 | L10: 1190 | M10: 755 | N10: 320 | O10: x | P10: Change in trade receivables | Q10: =-(K18-J18) -> 177381 | R10: =-(L18-K18) -> -1936259 | S10: =-(M18-L18) -> 375055 | T10: =-(N18-M18) -> -1287118
B11: Total depreciation, amortization & depletion | C11: -393099 | D11: -342652 | E11: -584234 | F11: -352969 | G11: -406658 | H11: x | I11: Other intangible assets | J11: 388159 | K11: 322360 | L11: 470059 | M11: 1110049 | N11: 915927 | O11: x | P11: Change in inventories | Q11: =-(K19-J19) -> -640807 | R11: =-(L19-K19) -> -268219 | S11: =-(M19-L19) -> -738763 | T11: =-(N19-M19) -> -70619
B12: Total operating expense | C12: -10252064 | D12: -8694921 | E12: -11771660 | F12: -13217410 | G12: -13843795 | I12: Tangible fixed assets | J12: 115120 | K12: 164109 | L12: 292008 | M12: 341765 | N12: 598899 | O12: x | P12: Change in other current assets | Q12: =-(K21-J21) -> 31256 | R12: =-(L21-K21) -> 746212 | S12: =-(M21-L21) -> -823710 | T12: =-(N21-M21) -> 320814
B13: Operating profit (loss) EBIT | C13: 308655 | D13: 546866 | E13: 889046 | F13: 1255732 | G13: 1106409 | I13: Investments | J13: 50270 | K13: 50270 | L13: 50270 | M13: 50270 | N13: 50270 | O13: x | P13: Change in trade payables | Q13: =K46-J46 -> -24329 | R13: =L46-K46 -> 746745 | S13: =M46-L46 -> 74011 | T13: =N46-M46 -> -584804
B14: Finance Revenue | C14: 584 | D14: 291 | E14: 258 | F14: 333 | G14: 74265 | I14: Deferred tax assets | J14: 0 | K14: 0 | L14: 0 | M14: 0 | N14: 0 | O14: x
B15: Finance Expense | C15: -191809 | D15: -166922 | E15: -173690 | F15: -240050 | G15: -382279 | I15: Other non-current receivables and financial assets | J15: 0 | K15: 0 | L15: 0 | M15: 0 | N15: 0 | O15: x | P15: change in current tax | Q15: =K48-J48 -> 17706 | R15: =L48-K48 -> 112101 | S15: =M48-L48 -> -79920 | T15: =N48-M48 -> 29474
B16: Other non-operating and financial income (expenses) | C16: -119 | D16: -62 | E16: -33 | F16: -14 | G16: -46 | I16: Total non-current assets | J16: 577699 | K16: 563008 | L16: 836581 | M16: 1533059 | N16: 1597153 | P16: Change in other current liabilities | Q16: =K49-J49 -> 16482 | R16: =L49-K49 -> 138986 | S16: =M49-L49 -> 179426 | T16: =N49-M49 -> 94321
B17: Financial profit (loss) | C17: -191344 | D17: -166693 | E17: -173465 | F17: -239731 | G17: -308060 | I17: Current assets | P17: Cash flow from operating activities | Q17: =SUM(Q7:Q16) -> 225091 | R17: =SUM(R7:R16) -> 637608 | S17: =SUM(S7:S16) -> 115848 | T17: =SUM(T7:T16) -> -418985
B18: Financial assets adjustments | C18: -89095 | D18: 0 | E18: 0 | F18: 0 | G18: 0 | I18: Trade receivables | J18: 3697489 | K18: 3520108 | L18: 5456367 | M18: 5081312 | N18: 6368430 | O18: x
B19: Profit (loss) before tax (PBT) | C19: 28216 | D19: 380173 | E19: 715581 | F19: 1016001 | G19: 798349 | I19: Inventories | J19: 1244471 | K19: 1885278 | L19: 2153497 | M19: 2892260 | N19: 2962879 | O19: x | P19: Purchase of PPE | Q19: =-((K12-D11)-(J12-C11)) -> 1458 | R19: =-((L12-E11)-(K12-D11)) -> -369481 | S19: =-((M12-F11)-(L12-E11)) -> 181508 | T19: =-((N12-G11)-(M12-F11)) -> -310823
B20: Income taxes | C20: -8512 | D20: -75423 | E20: -201773 | F20: -239221 | G20: -126060 | I20: Cash and cash equivalents | J20: 4873 | K20: 6128 | L20: 9204 | M20: 16924 | N20: 29539 | P20: Purchase of other LT investments | Q20: =-(K13-J13+K15-J15) -> 0 | R20: =-(L13-K13+L15-K15) -> 0 | S20: =-(M13-L13+M15-L15) -> 0 | T20: =-(N13-M13+N15-M15) -> 0
B21: NET PROFIT (PAT) | C21: 19704 | D21: 304750 | E21: 513808 | F21: 776780 | G21: 672289 | H21: x | I21: Other current assets and financial current assets | J21: 1307301 | K21: 1276045 | L21: 529833 | M21: 1353543 | N21: 1032729 | O21: x | P21: Other assets | Q21: =-(K9-J9+K10-J10+K11-J11+K14-J14) -> 63680 | R21: =-(L9-K9+L10-K10+L11-K11+L14-K14) -> -145674 | S21: =-(M9-L9+M10-L10+M11-L11+M14-L14) -> -646721 | T21: =-(N9-M9+N10-M10+N11-M11+N14-M14) -> 193040
I22: Total current assets | J22: 6254134 | K22: 6687559 | L22: 8148901 | M22: 9344039 | N22: 10393577 | P22: Cash flow from investing activities | Q22: =SUM(Q19:Q21) -> 65138 | R22: =SUM(R19:R21) -> -515155 | S22: =SUM(S19:S21) -> -465213 | T22: =SUM(T19:T21) -> -117783
I23: Assets held for sale and discounting operations
I24: TOTAL ASSETS | J24: 6831833 | K24: 7250567 | L24: 8985482 | M24: 10877098 | N24: 11990730 | P24: Increase in long term liabilities | Q24: =K42-J42 -> 623157 | R24: =L42-K42 -> 724080 | S24: =M42-L42 -> 1168222 | T24: =N42-M42 -> -239578
P25: Change in current liabilities for banks and loans | Q25: =K47-J47 -> -546049 | R25: =L47-K47 -> 766130 | S25: =M47-L47 -> -280686 | T25: =N47-M47 -> 1173788
I26: EQUITY AND LIABILITIES | P26: Decrease in other long term liabilities | Q26: =K43-J43+K41-J41+K40-J40+K39-J39 -> 27014 | R26: =L43-K43+L41-K41+L40-K40+L39-K39 -> -1266933 | S26: =M43-L43+M41-L41+M40-L40+M39-L39 -> 53781 | T26: =N43-M43+N41-M41+N40-M40+N39-M39 -> -31856
I27: Equity | P27: Proceeds from share issuance | Q27: =K28-J28 -> 0 | R27: =L28-K28 -> 0 | S27: =M28-L28 -> 0 | T27: =N28-M28 -> 0
I28: Share Capital | J28: 100000 | K28: 100000 | L28: 100000 | M28: 100000 | N28: 100000 | O28: x | P28: Cash flow from financing activities | Q28: =SUM(Q24:Q27) -> 104122 | R28: =SUM(R24:R27) -> 223277 | S28: =SUM(S24:S27) -> 941317 | T28: =SUM(T24:T27) -> 902354
I29: Other reserves | J29: 542433 | K29: 542436 | L29: 542434 | M29: 542436 | N29: 542433
I30: Retained earnings | J30: 0 | K30: 19704 | L30: 324454 | M30: 838262 | N30: 1615043 | P30: Net change in cash actual | Q30: =Q37-Q35 -> 1255 | R30: =R37-R35 -> 3076 | S30: =S37-S35 -> 7720 | T30: =T37-T35 -> 12615
P31: Net change in cash computed | Q31: =Q28+Q22+Q17 -> 394351 | R31: =R28+R22+R17 -> 345730 | S31: =S28+S22+S17 -> 591952 | T31: =T28+T22+T17 -> 365586
P32: Adjustment for cash flow recoinciliation | Q32: =Q30-Q31 -> -393096 | R32: =R30-R31 -> -342654 | S32: =S30-S31 -> -584232 | T32: =T30-T31 -> -352971
I33: Group profit (loss) for the period | J33: 19704 | K33: 304750 | L33: 513808 | M33: 776780 | N33: 672289 | P33: Adjusted net change in cash computed | Q33: =Q31+Q32 -> 1255 | R33: =R31+R32 -> 3076 | S33: =S31+S32 -> 7720 | T33: =T31+T32 -> 12615
I34: Total Equity Attributable to Equity Holders of the Parent | J34: 662137 | K34: 966890 | L34: 1480696 | M34: 2257478 | N34: 2929765
I35: Non-controlling-interest | J35: 0 | K35: 0 | L35: 0 | M35: 0 | N35: 0 | P35: Beginning | Q35: =J20 -> 4873 | R35: =K20 -> 6128 | S35: =L20 -> 9204 | T35: =M20 -> 16924
I36: TOTAL CONSOLIDATED EQUITY | J36: 662137 | K36: 966890 | L36: 1480696 | M36: 2257478 | N36: 2929765 | P36: Ending computed | Q36: =Q33+Q35 -> 6128 | R36: =R33+R35 -> 9204 | S36: =S33+S35 -> 16924 | T36: =T33+T35 -> 29539
I37: Liabilities | P37: Ending actual | Q37: =K20 -> 6128 | R37: =L20 -> 9204 | S37: =M20 -> 16924 | T37: =N20 -> 29539
I38: Non-current liabilities
I39: Provisions for risks and charges | J39: 0 | K39: 0 | L39: 0 | M39: 0 | N39: 0 | O39: x
I40: Employee benefits | J40: 193620 | K40: 220634 | L40: 253701 | M40: 307482 | N40: 275626 | O40: x
I41: Deferred tax liabilities | J41: 0 | K41: 0 | L41: 0 | M41: 0 | N41: 0 | O41: x
I42: Non-current liabilities to banks and other financial istitutions | J42: 1967673 | K42: 2590830 | L42: 3314910 | M42: 4483132 | N42: 4243554 | O42: x
I43: Other non-current liabilities | J43: 1300000 | K43: 1300000 | L43: 0 | M43: 0 | N43: 0 | O43: x
I44: Total non-current liabilities | J44: 3461293 | K44: 4111464 | L44: 3568611 | M44: 4790614 | N44: 4519180
I45: Current liabilities
I46: Trade payables | J46: 1047973 | K46: 1023644 | L46: 1770389 | M46: 1844400 | N46: 1259596 | O46: x
I47: Current liabilities to banks and other financial institutions | J47: 954402 | K47: 408353 | L47: 1174483 | M47: 893797 | N47: 2067585 | O47: x
I48: Current tax payables | J48: 25687 | K48: 43393 | L48: 155494 | M48: 75574 | N48: 105048 | O48: x
I49: Other current liabilities | J49: 680341 | K49: 696823 | L49: 835809 | M49: 1015235 | N49: 1109556 | O49: x
I50: Total current liabilities | J50: 2708403 | K50: 2172213 | L50: 3936175 | M50: 3829006 | N50: 4541785
I51: Libilities held for sale and discountiung | J51: 0 | K51: 0 | L51: 0 | M51: 0 | N51: 0
I52: TOTAL LIABILITIES | J52: 6169696 | K52: 6283677 | L52: 7504786 | M52: 8619620 | N52: 9060965
I53: TOTAL LIABILITIES AND EQUITY | J53: 6831833 | K53: 7250567 | L53: 8985482 | M53: 10877098 | N53: 11990730

Sheet Ratio
B1: Luis Trenker
B2: ADDITIONAL INFORMATION FOR PROFITABILITY ANALYSIS
E3: 2021 | F3: 2022 | G3: 2023 | H3: 2024
B4: OA | C4: Operating Assets | E4: ='[1]Reformulated balance sheet'!D63 -> 6766164 | F4: ='[1]Reformulated balance sheet'!E63 -> 8845278 | G4: ='[1]Reformulated balance sheet'!F63 -> 10164691 | H4: ='[1]Reformulated balance sheet'!G63 -> 11515958
B5: OL | C5: Operating Liabilites | E5: ='[1]Reformulated balance sheet'!D76 -> 1763860 | F5: ='[1]Reformulated balance sheet'!E76 -> 2761692 | G5: ='[1]Reformulated balance sheet'!F76 -> 2935209 | H5: ='[1]Reformulated balance sheet'!G76 -> 2474200
B6: NOA | C6: Net Operating Assets | E6: =E4-E5 -> 5002304 | F6: =F4-F5 -> 6083586 | G6: =G4-G5 -> 7229482 | H6: =H4-H5 -> 9041758
B7: FA | C7: Total Financial Assets | E7: ='[1]Reformulated balance sheet'!D67 -> 484403 | F7: ='[1]Reformulated balance sheet'!E67 -> 140204 | G7: ='[1]Reformulated balance sheet'!F67 -> 712407 | H7: ='[1]Reformulated balance sheet'!G67 -> 474772
B8: FL | C8: Financial Liabilities | E8: ='[1]Reformulated balance sheet'!D83 -> 4519817 | F8: ='[1]Reformulated balance sheet'!E83 -> 4743094 | G8: ='[1]Reformulated balance sheet'!F83 -> 5684411 | H8: ='[1]Reformulated balance sheet'!G83 -> 6586765
B9: NFO (NFA) | C9: Net Financial Obligation (Net Financial Assets) | E9: =E8-E7 -> 4035414 | F9: =F8-F7 -> 4602890 | G9: =G8-G7 -> 4972004 | H9: =H8-H7 -> 6111993
C10: Equity | E10: ='[1]Reformulated balance sheet'!D89 -> 966890 | F10: ='[1]Reformulated balance sheet'!E89 -> 1480696 | G10: ='[1]Reformulated balance sheet'!F89 -> 2257478 | H10: ='[1]Reformulated balance sheet'!G89 -> 2929765
B11: NOA | C11: Average NOA | F11: =(F6+E6)/2 -> 5542945 | G11: =(G6+F6)/2 -> 6656534 | H11: =(H6+G6)/2 -> 8135620
C12: Average Total Financial Assets | F12: =(F7+E7)/2 -> 312303.5 | G12: =(G7+F7)/2 -> 426305.5 | H12: =(H7+G7)/2 -> 593589.5
C13: Average Total Financial Liabilities | F13: =(F8+E8)/2 -> 4631455.5 | G13: =(G8+F8)/2 -> 5213752.5 | H13: =(H8+G8)/2 -> 6135588
B14: NFO (NFA) | C14: Average Net Financial Obligation (Net Financial Assets) | F14: =(F9+E9)/2 -> 4319152 | G14: =(G9+F9)/2 -> 4787447 | H14: =(H9+G9)/2 -> 5541998.5
B15: EQUITY | C15: Average Equity | F15: =(F10+E10)/2 -> 1223793 | G15: =(G10+F10)/2 -> 1869087 | H15: =(H10+G10)/2 -> 2593621.5
C16: Account Receivable | E16: ='[1]Reformulated balance sheet'!D56 -> 1192500 | F16: ='[1]Reformulated balance sheet'!E56 -> 1268047 | G16: ='[1]Reformulated balance sheet'!F56 -> 1367114 | H16: ='[1]Reformulated balance sheet'!G56 -> 899391
C17: Inventory | E17: ='[1]Reformulated balance sheet'!D57 -> 1885278 | F17: ='[1]Reformulated balance sheet'!E57 -> 2153497 | G17: ='[1]Reformulated balance sheet'!F57 -> 2892260 | H17: ='[1]Reformulated balance sheet'!G57 -> 2962879
C18: Accounts Payable | E18: ='[1]Reformulated balance sheet'!D71 -> 1023644 | F18: ='[1]Reformulated balance sheet'!E71 -> 1770389 | G18: ='[1]Reformulated balance sheet'!F71 -> 1844400 | H18: ='[1]Reformulated balance sheet'!G71 -> 1259596
C19: Average Account Receivable | F19: =(F16+E16)/2 -> 1230273.5 | G19: =(G16+F16)/2 -> 1317580.5 | H19: =(H16+G16)/2 -> 1133252.5
C20: Average Inventory | F20: =(F17+E17)/2 -> 2019387.5 | G20: =(G17+F17)/2 -> 2522878.5 | H20: =(H17+G17)/2 -> 2927569.5
C21: Average Accounts Payable | F21: =(F18+E18)/2 -> 1397016.5 | G21: =(G18+F18)/2 -> 1807394.5 | H21: =(H18+G18)/2 -> 1551998
C22: Revenues | E22: ='[1]Reformulated Income statement'!D5 -> 9241787 | F22: ='[1]Reformulated Income statement'!E5 -> 12660706 | G22: ='[1]Reformulated Income statement'!F5 -> 14473142 | H22: ='[1]Reformulated Income statement'!G5 -> 14950204
C23: COGS (manufacturing) or Cost of Sales (other industries) | E23: ='[1]Reformulated Income statement'!D7 -> -4922052 | F23: ='[1]Reformulated Income statement'!E7 -> -6273959 | G23: ='[1]Reformulated Income statement'!F7 -> -7792575 | H23: ='[1]Reformulated Income statement'!G7 -> -6960697
C24: Gross Profit | E24: =E22+E23 -> 4319735 | F24: =F22+F23 -> 6386747 | G24: =G22+G23 -> 6680567 | H24: =H22+H23 -> 7989507
B25: NOPAT CORE | C25: Core Operating Income from sales (After tax effect) | E25: ='[1]Reformulated Income statement'!D72 -> -60840.5 | F25: ='[1]Reformulated Income statement'!E72 -> 317391.31 | G25: ='[1]Reformulated Income statement'!F72 -> 65251.228 | H25: ='[1]Reformulated Income statement'!G72 -> 881265.58
B26: UI | C26: Unusual Item (after tax effect)
B27: NOPAT | C27: NOPAT | E27: ='[1]Reformulated Income statement'!D76 -> 438372.57 | F27: ='[1]Reformulated Income statement'!E76 -> 638360.92 | G27: ='[1]Reformulated Income statement'!F76 -> 960065.49 | H27: ='[1]Reformulated Income statement'!G76 -> 931706.06
C28: Financial Income (after tax effect) | E28: ='[1]Reformulated Income statement'!D78 -> 291 | F28: ='[1]Reformulated Income statement'!E78 -> 258 | G28: ='[1]Reformulated Income statement'!F78 -> 333 | H28: ='[1]Reformulated Income statement'!G78 -> 74265
C29: Financial Expenses (after tax effect) | E29: ='[1]Reformulated Income statement'!D79 -> -166922 | F29: ='[1]Reformulated Income statement'!E79 -> -173690 | G29: ='[1]Reformulated Income statement'!F79 -> -240050 | H29: ='[1]Reformulated Income statement'!G79 -> -382279
B30: NFE | C30: Net financial expense (income) after tax | E30: ='[1]Reformulated Income statement'!D83 -> -133622.57 | F30: ='[1]Reformulated Income statement'!E83 -> -124552.92 | G30: ='[1]Reformulated Income statement'!F83 -> -183285.49 | H30: ='[1]Reformulated Income statement'!G83 -> -259417.06
C31: EBT | E31: ='[1]Reformulated Income statement'!D44 -> 380173 | F31: ='[1]Reformulated Income statement'!E44 -> 715581 | G31: ='[1]Reformulated Income statement'!F44 -> 1016001 | H31: ='[1]Reformulated Income statement'!G44 -> 798349
C32: Net Income from continuing operations | E32: ='[1]Reformulated Income statement'!D46 -> 304750 | F32: ='[1]Reformulated Income statement'!E46 -> 513808 | G32: ='[1]Reformulated Income statement'!F46 -> 776780 | H32: ='[1]Reformulated Income statement'!G46 -> 672289
C33: Net Income | E33: ='[1]Reformulated Income statement'!D50 -> 304750 | F33: ='[1]Reformulated Income statement'!E50 -> 513808 | G33: ='[1]Reformulated Income statement'!F50 -> 776780 | H33: ='[1]Reformulated Income statement'!G50 -> 672289
C34: Net Income attribuitable to common shareholder
C35: Gross Tangible Assets | E35: ='[1]Reformulated balance sheet'!D58 -> 164109 | F35: ='[1]Reformulated balance sheet'!E58 -> 292008 | G35: ='[1]Reformulated balance sheet'!F58 -> 341765 | H35: ='[1]Reformulated balance sheet'!G58 -> 598899
C36: Depreciation | E36: ='[1]Income statement'!C27 -> 44125 | F36: ='[1]Income statement'!D27 -> 50982 | G36: ='[1]Income statement'!E27 -> 65514 | H36: ='[1]Income statement'!F27 -> 104667
C37: Accumulated Depreciation | F37: =F36-E36 -> 6857 | G37: =G36-F36 -> 14532 | H37: =H36-G36 -> 39153
C38: PP&E net | E38: =E35-E36 -> 119984 | F38: =F35-F36 -> 241026 | G38: =G35-G36 -> 276251 | H38: =H35-H36 -> 494232
C39: Average Assets | F39: =('[1]Reformulated balance sheet'!E21+'[1]Reformulated balance sheet'!D21)/2 -> 8118024.5 | G39: =('[1]Reformulated balance sheet'!F21+'[1]Reformulated balance sheet'!E21)/2 -> 9931290 | H39: =('[1]Reformulated balance sheet'!G21+'[1]Reformulated balance sheet'!F21)/2 -> 11433914
B41: Table 4.e
B43: Luis Trenker S.r.l.
B44: GROWTH ANALYSIS
C45: Numerator | D45: Denominator | F45: 2022 | G45: 2023 | H45: 2024
B46: Revenues | C46: Revenues (t) - Revenues (t-1) | D46: Revenues (t-1) | F46: =(F22-E22)/E22 -> 0.36994133 | G46: =(G22-F22)/F22 -> 0.14315442 | H46: =(H22-G22)/G22 -> 0.032961882
B47: Core Operating Income | C47: CORE NOPAT (t) - CORE NOPAT (t-1) | D47: CORE NOPAT (t-1) | F47: =(F25-E25)/E25 -> -6.2167768 | G47: =(G25-F25)/F25 -> -0.79441394 | H47: =(H25-G25)/G25 -> 12.505732
B48: Operating Income | C48: NOPAT (t) - NOPAT (t-1) | D48: NOPAT (t-1) | F48: =(F27-E27)/E27 -> 0.45620637 | G48: =(G27-F27)/F27 -> 0.50395405 | H48: =(H27-G27)/G27 -> -0.029539064
B49: NOA | C49: NOA (t) - NOA (t-1) | D49: NOA (t-1) | F49: =(F6-E6)/E6 -> 0.21615679 | G49: =(G6-F6)/F6 -> 0.18835864 | H49: =(H6-G6)/G6 -> 0.25067854
B51: Table 5.e
B53: PROFITABILITY ANALYSIS
F54: 2022 | G54: 2023 | H54: 2024
B55: SUMMARY MEASURE
B56: ROE | C56: Net Income | D56: Average Equity | F56: =F33/F15 -> 0.41984878 | G56: =G33/G15 -> 0.41559328 | H56: =H33/H15 -> 0.2592086
B57: RNOA | C57: NOPAT | D57: Average NOA | F57: =F27/F11 -> 0.11516638 | G57: =G27/G11 -> 0.14422904 | H57: =H27/H11 -> 0.11452183
B58: ROA | C58: Net Income | D58: Average Assets | F58: =F33/F39 -> 0.063292246 | G58: =G33/G39 -> 0.078215418 | H58: =H33/H39 -> 0.058797801
B59: Profit magin for ROA | C59: Net Income | D59: Revenues | F59: =F33/F22 -> 0.040582887 | G59: =G33/G22 -> 0.053670447 | H59: =H33/H22 -> 0.04496855
B60: Asset Turnover for ROA | C60: Revenues | D60: Average Assets | F60: =F22/F39 -> 1.5595797 | G60: =G22/G39 -> 1.4573275 | H60: =H22/H39 -> 1.3075316
B61: Financial leverage for ROA | C61: Average Assets | D61: Average Equity | F61: =F39/F15 -> 6.6334948 | G61: =G39/G15 -> 5.3134445 | H61: =H39/H15 -> 4.4084744
B62: CHECK | F62: 0 | G62: 0 | H62: 0
B64: Table 6.e
B66: FIRST LEVEL BREAK DOWN
C67: Distinguish financing, operating and leverage
C68: Numerator | D68: Denominator | F68: 2022 | G68: 2023 | H68: 2024
B69: ROE | C69: RNOA+(FLEV * (RONA-NBC)*X | F69: =F57+(F72*F73) -> 0.41984878 | G69: =G57+(G72*G73) -> 0.41559328 | H69: =H57+(H72*H73) -> 0.2592086
B70: RNOA | C70: NOPAT | D70: Avg NOA | F70: =F27/F11 -> 0.11516638 | G70: =G27/G11 -> 0.14422904 | H70: =H27/H11 -> 0.11452183
B71: Net Borrowing Cost/RNFA | C71: Net financial expense (income) after tax | D71: Average Net Financial Obligation (Net Financial Assets) | F71: =-F30/F14 -> 0.028837356 | G71: =-G30/G14 -> 0.0382846 | H71: =-H30/H14 -> 0.046809298
B72: FLEV | C72: Average Net Financial Obligation (Net Financial Assets) | D72: Average Equity | F72: =F14/F15 -> 3.5293158 | G72: =G14/G15 -> 2.5613826 | H72: =H14/H15 -> 2.13678
B73: SPREAD | C73: Spread=RNOA - NBC | F73: =F70-F71 -> 0.086329027 | G73: =G70-G71 -> 0.10594444 | H73: =H70-H71 -> 0.067712528
B74: FLEV*SPREAD | F74: =F72*F73 -> 0.3046824 | G74: =G72*G73 -> 0.27136424 | H74: =H72*H73 -> 0.14468677
B75: X (Extr. items and Disc. Op Effect) | C75: Net Income | D75: Net Income from continuing operations
B76: CHECK | F76: 0 | G76: 0 | H76: 0
B79: SECOND LEVEL BREAK DOWN
C80: Distinguish financing, operating and leverage
C81: Numerator | D81: Denominator | F81: 2022 | G81: 2023 | H81: 2024
B82: RNOA
B83: Profit Margin (ROS) | C83: NOPAT | D83: Revenues | F83: =F27/F22 -> 0.050420642 | G83: =G27/G22 -> 0.066334283 | H83: =H27/H22 -> 0.062320625
B84: Unusual or Infrequent items | C84: Unusual or Infrequent items | D84: Avg NOA
B85: Core RNOA | C85: Core Operating Income from sales (After tax effect) | D85: Avg NOA | F85: =F25/F11 -> 0.057260411 | G85: =G25/G11 -> 0.0098025831 | H85: =H25/H11 -> 0.10832187
B86: Core Profit Margin (ROS) | C86: Core Operating Income from sales (After tax effect) | D86: Revenues | F86: =F25/F22 -> 0.025069006 | G86: =G25/G22 -> 0.0045084355 | H86: =H25/H22 -> 0.058946726
B87: Asset Turnover (CT) | C87: Revenues | D87: Avg NOA | F87: =F22/F11 -> 2.2841118 | G87: =G22/G11 -> 2.174276 | H87: =H22/H11 -> 1.8376232
C88: Net Borrowing Cost (Return from net financial assets) drivers
B89: Net Borrowing Cost/RNFA
B90: ROD | C90: Financial Expenses (after tax effect) | D90: Average Total Financial Liabilities | F90: =F29/F13 -> -0.03750225 | G90: =G29/G13 -> -0.046041695 | H90: =H29/H13 -> -0.062305194
B91: Weight of Financial Obbligation (FO) | C91: Average Total Financial Liabilities | D91: Average Net Financial Obligation (Net Financial Assets) | F91: =F13/F14 -> 1.0723067 | G91: =G13/G14 -> 1.0890465 | H91: =H13/H14 -> 1.1071075
B92: RFA (FI/FA) | C92: Financial Income (after tax effect) | D92: Average Total Financial Assets | F92: =F28/F12 -> 0.00082611946 | G92: =G28/G12 -> 0.00078112996 | H92: =H28/H12 -> 0.12511171
B93: Weight of Financial Assets (FA) | C93: Average Total Financial Assets | D93: Average Net Financial Obligation (Net Financial Assets) | F93: =F12/F14 -> 0.07230667 | G93: =G12/G14 -> 0.089046521 | H93: =H12/H14 -> 0.10710748
B94: CHECK | F94: 0 | G94: 0 | H94: 0
B96: Table 7.e
B98: THIRD LEVEL BREAK DOWN
C99: Drivers of operating profitability
C100: Numerator | D100: Denominator | F100: 2022 | G100: 2023 | H100: 2024
B102: Gross Profit | C102: Gross Profit | D102: Sales | F102: =F24/F22 -> 0.50445425 | G102: =G24/G22 -> 0.46158374 | H102: =H24/H22 -> 0.53440789
B103: Other operating expense | C103: Other operating expense | D103: Revenues
C104: Capital Turnover drivers | F104: 2022 | G104: 2023 | H104: 2024
B105: Accounts Receivable Turnover (ART) | C105: Sales | D105: Average Account Receivable | F105: =F22/F19 -> 10.290969 | G105: =G22/G19 -> 10.984636 | H105: =H22/H19 -> 13.192297
B106: Inventory Turnover (INVT) | C106: COGS | D106: Average Inventory | F106: =ABS(F23/F20) -> 3.1068624 | G106: =ABS(G23/G20) -> 3.0887635 | H106: =ABS(H23/H20) -> 2.3776368
B107: Accounts Payable Turnover (APT) | C107: COGS | D107: Average Accounts Payable | F107: =ABS(F23/F21) -> 4.4909699 | G107: =ABS(G23/G21) -> 4.3114965 | H107: =ABS(H23/H21) -> 4.484991
B108: Days' Sales Outstanding Receivable | C108: 365 | D108: Accounts Receivable Turnover | F108: =365/F105 -> 35.467993 | G108: =365/G105 -> 33.228229 | H108: =365/H105 -> 27.66766
B109: Days' Sales in Inventory | C109: 365 | D109: Inventory Turnover | F109: =365/F106 -> 117.48187 | G109: =365/G106 -> 118.17026 | H109: =365/H106 -> 153.51377
B110: Days' Purchases Outstanding Payable | C110: 365 | D110: Accounts Payable Turnover | F110: =365/F107 -> 81.274204 | G110: =365/G107 -> 84.657381 | H110: =365/H107 -> 81.38255
B111: Operating Cycle | C111: Days' Sales Outstanding Receivable + Days' Sales in Inventory | F111: =F108+F109 -> 152.94986 | G111: =G108+G109 -> 151.39849 | H111: =H108+H109 -> 181.18143
...

Sheet Income statement
A1: Profit and loss account
A2: thousands of euros
A3: Unconsolidated | B3: 31/03/2020 EUR | C3: 31/03/2021 EUR | D3: 31/03/2022 EUR | E3: 31/03/2023 EUR | F3: 31/03/2024 EUR
B4: 12 months Detailed ICS | C4: 12 months Detailed ICS | D4: 12 months Detailed ICS | E4: 12 months Detailed ICS | F4: 12 months Detailed ICS
A5: A. TOTAL VALUE OF PRODUCTION | B5: 10560719 | C5: 9241787 | D5: 12660706 | E5: 14473142 | F5: 14950204
A6: A.1. Revenues from sales and services | B6: 9712939 | C6: 8552816 | D6: 11619465 | E6: 13782014 | F6: 14294364
A7: A.2. Changes in inventories | B7: 0 | C7: 0 | D7: 0 | E7: 0 | F7: 0
A8: A.3. Changes in contract work in progress | B8: 0 | C8: 0 | D8: 0 | E8: 0 | F8: 0
A9: A.2. + A.3. Total changes | B9: 0 | C9: 0 | D9: 0 | E9: 0 | F9: 0
A10: A.4. Additions to fixed assets | B10: 0 | C10: 0 | D10: 0 | E10: 0 | F10: 0
A11: A.5. Other revenue | B11: 847780 | C11: 688971 | D11: 1041241 | E11: 691128 | F11: 655840
A12: operating grants | B12: 641183 | C12: 260024 | D12: 445901 | E12: 404719 | F12: 360311
A14: B. TOTAL PRODUCTION COSTS | B14: 10252064 | C14: 8694921 | D14: 11771660 | E14: 13217410 | F14: 13843795
A15: B.6. Raw, consum. mat. and goods for resale | B15: 5324267 | C15: 4922052 | D15: 6273959 | E15: 7792575 | F15: 6960697
A16: B.7. Services | B16: 2733445 | C16: 2242963 | D16: 2473024 | E16: 2871646 | F16: 3194159
A17: B.8. Use of third parties assets | B17: 508533 | C17: 357317 | D17: 562664 | E17: 740801 | F17: 873725
... A40: C.15. Total income from equity investments | B40: 0 | C40: 0 | D40: 0 | E40: 0 | F40: 0
A41: of which: from subsidiaries, associated, parent cies and cies under parent cies control | B41: n.a. | C41: n.a. | D41: n.a. | E41: n.a. | F41: n.a.
A42: of which: from parent companies | B42: 0 | C42: 0 | D42: 0 | E42: 0 | F42: 0
A43: of which: from companies under parent companies control | B43: 0 | C43: 0 | D43: 0 | E43: 0 | F43: 0
A44: C.16. Total other financial income | B44: 584 | C44: 291 | D44: 258 | E44: 333 | F44: 74265
A45: C.16.a. From financial receivables | B45: 0 | C45: 0 | D45: 0 | E45: 0 | F45: 0
A46: of which: from subsidiaries, associated, parent cies and cies under parent cies control | B46: n.a. | C46: n.a. | D46: n.a. | E46: n.a. | F46: n.a.
A47: of which: from companies under parent companies control | B47: 0 | C47: 0 | D47: 0 | E47: 0 | F47: 0
A48: C.16.b. From securities held as fixed assets | B48: 0 | C48: 0 | D48: 0 | E48: 0 | F48: 0
A49: C.16.c. From securities held as current assets | B49: 0 | C49: 0 | D49: 0 | E49: 0 | F49: 0
A50: C.16.b+c. From securities | B50: 0 | C50: 0 | D50: 0 | E50: 0 | F50: 0
A51: C.16.d. Income other than the above | B51: 584 | C51: 291 | D51: 258 | E51: 333 | F51: 74265
A52: of which: from subsidiaries, associated, parent cies and cies under parent cies control | B52: n.a. | C52: 0 | D52: 0 | E52: 0 | F52: 0
A53: of which: from companies under parent companies control | B53: 0 | C53: 0 | D53: 0 | E53: 0 | F53: 0
A54: C.17. Total financial charges | B54: 191809 | C54: 166922 | D54: 173690 | E54: 240050 | F54: 382279
A55: of which: from financial receivables subs and assoc. | B55: n.a. | C55: 0 | D55: 0 | E55: 0 | F55: 0
A56: of which: from companies under parent companies control | B56: 0 | C56: 0 | D56: 0 | E56: 0 | F56: 0
A57: C.17.bis Profit and Loss on Foreign Exchange | B57: -119 | C57: -62 | D57: -33 | E57: -14 | F57: -46
A59: D. TOTAL FINANCIAL ASSETS ADJUSTMENTS | B59: -89095 | C59: 0 | D59: 0 | E59: 0 | F59: 0
A60: D.18. Total Revaluations | B60: 0 | C60: 0 | D60: 0 | E60: 0 | F60: 0
A61: D.18.a. Reval. of equity investments | B61: 0 | C61: 0 | D61: 0 | E61: 0 | F61: 0
A62: D.18.b. Reval. of other financial assets | B62: 0 | C62: 0 | D62: 0 | E62: 0 | F62: 0
A63: D.18.c. Reval. of securities | B63: 0 | C63: 0 | D63: 0 | E63: 0 | F63: 0
A64: D.18.d. Reval. of derivatives | B64: 0 | C64: 0 | D64: 0 | E64: 0 | F64: 0
A65: Reval. of financial instruments for cash pooling | B65: 0 | C65: 0 | D65: 0 | E65: 0 | F65: 0
A66: D.19. Total Writedowns | B66: 89095 | C66: 0 | D66: 0 | E66: 0 | F66: 0
A67: D.19.a. Writedowns of equity invest. | B67: 89095 | C67: 0 | D67: 0 | E67: 0 | F67: 0
A68: D.19.b. Writedowns of other fin. Ass. | B68: 0 | C68: 0 | D68: 0 | E68: 0 | F68: 0
... A89: 21. PROFIT (LOSS) | B89: 19704 | C89: 304750 | D89: 513808 | E89: 776780 | F89: 672289
A90: PROFIT (LOSS) THIRD PARTIES | B90: n.a. | C90: n.a. | D90: n.a. | E90: n.a. | F90: n.a.
A91: PROFIT (LOSS) GROUP | B91: 19704 | C91: 304750 | D91: 513808 | E91: 776780 | F91: 672289
A93: Employees | B93: 36 | C93: 38 | D93: 40 | E93: 42 | F93: 48

Sheet Ratios
A1: Ratios
B3: Unconsolidated | C3: 31/03/2024 EUR | D3: 31/03/2023 EUR | E3: 31/03/2022 EUR | F3: 31/03/2021 EUR | G3: 31/03/2020 EUR | H3: 31/03/2019 EUR
C4: 12 months Detailed ICS | D4: 12 months Detailed ICS | E4: 12 months Detailed ICS | F4: 12 months Detailed ICS | G4: 12 months Detailed ICS | H4: 12 months Detailed ICS
B5: 1. Financial indicators
B7: - Liquidity ratio | C7: 1.61 | D7: 1.63 | E7: 1.49 | F7: 1.99 | G7: 1.48 | H7: 1.18
B8: - Current ratio | C8: 2.31 | D8: 2.45 | E8: 2.07 | F8: 2.94 | G8: 1.97 | H8: 1.46
B9: - Current liabilities/Tot ass. | C9: 0.5 | D9: 0.44 | E9: 0.53 | F9: 0.34 | G9: 0.44 | H9: 0.56
B10: - Long/med term liab/Tot ass. | C10: 0.5 | D10: 0.56 | E10: 0.47 | F10: 0.66 | G10: 0.56 | H10: 0.44
B11: - Tang. fixed ass./Share funds | C11: 0.2 | D11: 0.15 | E11: 0.2 | F11: 0.17 | G11: 0.17 | H11: 0.18
B12: - Depr./Tang. fixed assets | C12: n.a. | D12: n.a. | E12: n.a. | F12: n.a. | G12: n.a. | H12: n.a.
B13: - Leverage | C13: 4.09 | D13: 4.82 | E13: 6.07 | F13: 7.5 | G13: 10.32 | H13: 11.2
B14: - Coverage of fixed assets | C14: 4.49 | D14: 4.4 | E14: 5.73 | F14: 8.63 | G14: 6.8 | H14: 4.91
B15: - Banks/Turnover | C15: 35.17 | D15: 28.68 | E15: 25.19 | F15: 32.45 | G15: 27.67 | H15: 25.15
B16: - Cost of debit | C16: 7.27 | D16: 5.78 | E16: 5.45 | F16: 5.57 | G16: 6.56 | H16: 5.98
B17: - Interest/Operating profit | C17: 3.96 | D17: 6.7 | E17: 8.48 | F17: 5.33 | G17: 3.66 | H17: 3.72
B18: - Interest/Turnover | C18: 2.56 | D18: 1.66 | E18: 1.37 | F18: 1.81 | G18: 1.82 | H18: 1.5
B19: - Solvency ratio | C19: 24.43 | D19: 20.75 | E19: 16.48 | F19: 13.34 | G19: 9.69 | H19: 8.93
B20: - Share funds/Liabilities | C20: 0.35 | D20: 0.28 | E20: 0.21 | F20: 0.16 | G20: 0.11 | H20: 0.1
B21: - Net Financial Position | C21: 5886637 | D21: 4714792 | E21: 4399459 | F21: 2565050 | G21: 2849112 | H21: 3938981
B22: - Debt/Equity ratio | C22: 2.15 | D22: 2.38 | E22: 3.03 | F22: 3.1 | G22: 4.41 | H22: 6.2
B23: - Debt/EBITDA ratio | C23: 4.17 | D23: 3.34 | E23: 3.05 | F23: 3.37 | G23: 4.16 | H23: 6.68
B25: 2. Management ratios
B27: - Total assets turnover (times) | C27: 1.19 | D27: 1.27 | E27: 1.29 | F27: 1.18 | G27: 1.42 | H27: 1.42
B28: - Working cap. turnover (times) | C28: 1.47 | D28: 1.6 | E28: 1.51 | F28: 1.46 | G28: 1.94 | H28: 2
B29: - Incidenza circolante operativo | C29: 17.41 | D29: 16.69 | E29: 13.04 | F29: 22.23 | G29: 23.88 | H29: 21.71
B30: - Stocks/Turnover (days) | C30: 72.34 | D30: 72.94 | E30: 62.08 | F30: 74.46 | G30: 43.01 | H30: 33.29
B31: - Stocks/Cost goods sold (days) | C31: 156.96 | D31: 149.66 | E31: 130.88 | F31: 160.73 | G31: 89.9 | H31: 64.85
B32: - Durata media dei crediti al lordo IVA (days) | C32: 21.96 | D32: 34.48 | E32: 36.56 | F32: 47.1 | G32: 80.38 | H32: 91.73
B33: - Durata media dei debiti al lordo IVA (days) | C33: 41.69 | D33: 59.03 | E33: 69.41 | F33: 49.67 | G33: 44.65 | H33: 54.12
B34: - Durata Ciclo Commerciale (days) | C34: 137.23 | D34: 125.11 | E34: 98.03 | F34: 158.16 | G34: 125.63 | H34: 102.46
B36: 3. Profitability ratios
B38: - EBITDA | C38: 1513067 | D38: 1608701 | E38: 1473280 | F38: 889518 | G38: 701754 | H38: 595594
B39: - EBITDA/Vendite | C39: 10.12 | D39: 11.12 | E39: 11.64 | F39: 9.62 | G39: 6.64 | H39: 5.59
B40: - Return on asset (ROA) | C40: 9.23 | D40: 11.54 | E40: 9.89 | F40: 7.54 | G40: 4.52 | H40: 6.75
B41: - Return on investment (ROI) | C41: 11.97 | D41: 16.45 | E41: 14.89 | F41: 10.38 | G41: 6.32 | H41: 10.5
B42: - Return on sales (ROS) | C42: 7.4 | D42: 8.68 | E42: 7.02 | F42: 5.92 | G42: 2.92 | H42: 4.56
B43: - Return on equity (ROE) | C43: 22.95 | D43: 34.41 | E43: 34.7 | F43: 31.52 | G43: 2.98 | H43: 32.6
B44: - Net P&L / Operating P&L | C44: 60.76 | D44: 61.86 | E44: 57.79 | F44: 55.73 | G44: 6.38 | H44: 43.14
B46: 4. Productivity ratios
B48: - Number of employees | C48: 48 | D48: 42 | E48: 40 | F48: 38 | G48: 36 | H48: 25
B49: - Turnover per employee | C49: 311460 | D49: 344600 | E49: 316520 | F49: 243200 | G49: 293350 | H49: 426370
B50: - Added value per employee | C50: 82610 | D50: 90300 | E50: 90040 | F50: 61640 | G50: 62730 | H50: 74260
B51: - Staff Costs per employee | C51: 51090 | D51: 51990 | E51: 53200 | F51: 38230 | G51: 43240 | H51: 50440
B52: - Turnover/Staff Costs | C52: 6.1 | D52: 6.63 | E52: 5.95 | F52: 6.36 | G52: 6.78 | H52: 8.45
B54: 5. Significant data
B56: - Net working capital | C56: 5531019 | D56: 5111968 | E56: 3986187 | F56: 3854148 | G56: 2469374 | H56: 1608138
B57: - Gross profit | C57: 7404286 | D57: 6728202 | E57: 5613726 | F57: 4271571 | G57: 4660352 | H57: 4749844
B58: - Net short term assets | C58: -2473254 | D58: -937553 | E58: -1468917 | F58: -117788 | G58: 152817 | H58: -287495
B59: - Share funds - Fixed assets | C59: 1332612 | D59: 724419 | E59: 644115 | F59: 403882 | G59: 84438 | H59: -50109
B60: - Cash Flow | C60: 1078947 | D60: 1129749 | E60: 1098042 | F60: 647402 | G60: 412803 | H60: 319499
